{"distanciaTotal":"80,8 km","tempoTotal":"1 h 6 min","rota":{"code":"Ok","routes":[{"geometry":"bapgC~`ifHu@d@kCdB`BzCbB~CdBbD`B|C`B~Ch@bAZj@DH`@b@FDp@p@d@l@dBdBzA|ANKLGLAN?VBJFRHfBr@jAd@PFJDp@VTHh@R|@ZbEzANDvGzBfDnAJL^Nl@RhFbBv@V~@Rp@JRDL@vAVBHFFHDF@F@BAFADEVGXGREVAp@Ej@Cd@Ad@Gf@GjAO~B]hAO~@OjAQbAQlAQh@GZGXCx@MtB]bAOn@Ij@GpAKf@@XDXHXLZTPNNb@L`@Pl@Hb@Ln@z@fHrAbLJv@h@~DTbB^~Cd@bENzAHrADzABvA@xA?dAChAG`BE~@ShCc@nEu@pHUbCe@vEe@|E]|DOlBOzCMdDEjEBzCDxBHpBN~BP|BN`BL`ANhAPnAPz@Lp@^lB`@xB\\rBh@~BdChMtJbf@PbAVnAzAxH^jB~Ldn@|Gh]jD~PbArFd@xBr@lDXtAZbBvC~NfBpIXrATrAXrAp@~CJr@h@`CBJxDrSxGd]VrAB\\n@~GBz@DnAAZEpBo@zXGdCGnDE~CUlLQ~EO`C_@rCi@`C{@zC_AhC_ApB}A~CkRx_@wAnCuA~BoAjBkAzAaB~A}ApA{AfA_BbAiLnGyM|H{JpFaAh@{CfBgShKeH~DcRnK}HlEgTzL}MtHoFvCoIvEiH`EkCxAcB`AmBbAaCtA{@h@w@j@_An@w@n@eAz@cAz@}@v@_A~@iAjAgAlAo@r@}@pAwBpCoB`CqBhCiA|AkDtE}HbKuHzJwH`Ko@|@aBvBoCnD{AnB}@nAoA~AmA`BeC|CkA~A_CzCwBpC}ArBuAhB{ElG_DbE{DdFwBpCGJ_MbP_FpGUVWT]V[TUPUT]`@q@|@OROTMTKRM^Sb@OVS`@yFpH}FpHgLlOEDSPYVi@b@q@l@[\\e@l@e@l@QVY`@MXMTQ`@Sb@[h@QV}G|IiF~GcIjKoMxPiCdDkCjDyH~Jg@p@gDlEuAfBgB`CiDvE{@fAi@r@iAxAc@`@YXURQNQJSHUDYD]By@D]HSHMJILILINGPITM\\MVMVIHKLQJUJk@HgCZuBZaJr@q@FaDReEZqC^cCPcG`@sJx@{Ir@yBNaA@gENqBBe@@kDXa@@a@C[E[S[I[C]BYDa@NKJMNM\\CTAT@XBTHPP\\TN`@l@Zx@F\\B`@Bf@\\tMp@b[JxB`@jHxAto@N`JRhHXnF^xOLrFL~EFbCHjElB|x@t@r\\L~FBvAx@d]\\rNbEnjBZpMZvNFfBZrNd@bTX~Ld@|RJrEJvEJtEZdN\\lN\\|Oj@|U^zO@^TpKTlHJfGF|IHhFFxBZzMl@|W`@pKPlFLxDFzBf@|Ux@x\\\\jHh@pGjApIhAbHR`Aj@bC|AlGr@zBnC~Hf@xAnAtCnAhCnAfC`@r@rA~BlCdEzBbDtB`DxB|CvAjBHLHLzEfHhD~EpI~LlFnIpBfD`A~AtAjCtCtGxCjHjBdFjApDrAtEl@dCvAvGxAfIv@dJFp@z@hJ\\nDd@xEz@xIZlDjAfMt@tHn@zGT~B`@xEZ|CJ~@TdCxFtl@tBzRp@dHp@pHHx@lAbMpCzZnClYtAlNj@fGN`CVbDf@tFbAjKtBbU^tDLvA\\nFd@rFd@`Fp@bHH~@n@fIJ`AjCpXdCdXdE`c@dAbLLvAt@|Hr@zHlAtMp@nLF`AV~ERzEZhIX~MFbJ?hMOzP_@zR_ApSu@fMcA|Ls@jHWfCiAvK}CdZ_DjZ{CxYMtAgC`VoCzWmAvL[bDi@fFwCxXsBxRi@`FcCbVmAnLmAdLcCxUgCnVcCnUgBbQCVa@|DqB`RwBtSkApKuA`Nc@tFKz@q@bHKdAs@xGgAbJOxAq@`HiDl[_@dDwBvRyDb_@oObyAcEz`@yA|M?\\aEtb@Gn@g@rEmChVcFvf@o@~Gg@nEu@~EMt@Wr@s@hAgM~NoD`EmB|B[^iBtBqB~BqCdDuBbCmC~C{@r@c@X_@P[Lc@TMDE@YT]\\OTKRAPQn@Sl@[r@a@n@e@l@m@`Ae@`A]~@WdAQjAK~@E~@AnABjAFv@R`BX`B`@hCXhBVbB`@hCn@hEhEpXtA|I|A|Jh@fDxBfNB^@\\AzBGzBBd@Hb@ZdAl@tAh@hAPd@Jf@~@hGLx@nDjUJj@`AnGPp@LdADj@Bh@Bj@?R@r@EP?PBLFLVn@n@fBV~@v@dFz@dFT|ARnAr@vDfAvGz@bGDZVxAj@lDn@lEn@rEj@fDJd@r@lEXnBRzAt@pEp@nEd@rCLt@d@zCF\\^bChAhHd@`DLbAx@vE\\|BNbAVrAVhBz@zFh@hD~AtJ@Nj@hDh@fDf@fDf@hDVdBDZn@tDn@fEcBXqDr@l@bEvB_@","legs":[{"steps":[{"geometry":"bapgC~`ifHu@d@kCdB","maneuver":{"bearing_after":326,"bearing_before":0,"location":[-48.384315,-22.369623],"modifier":"left","type":"depart"},"mode":"driving","driving_side":"right","name":"Avenida José Alves Mira","intersections":[{"out":0,"entry":[true],"bearings":[326],"location":[-48.384315,-22.369623]},{"out":3,"in":1,"entry":[true,false,false,true],"bearings":[60,150,240,330],"location":[-48.384509,-22.369351]}],"weight":16.6,"duration":16.6,"distance":129.6},{"geometry":"`{ogCjeifH`BzCbB~CdBbD`B|C`B~Ch@bAZj@DH`@b@","maneuver":{"bearing_after":234,"bearing_before":324,"location":[-48.38502,-22.368654],"modifier":"left","type":"turn"},"mode":"driving","driving_side":"right","name":"Rua Treze de Maio","intersections":[{"out":2,"in":1,"entry":[false,false,true,true],"bearings":[60,150,240,330],"location":[-48.38502,-22.368654]},{"out":2,"in":0,"entry":[false,true,true,true],"bearings":[60,150,240,330],"location":[-48.385801,-22.369144]},{"out":2,"in":0,"entry":[false,true,true,true],"bearings":[60,150,240,330],"location":[-48.3866,-22.369635]},{"out":2,"in":0,"entry":[false,true,true,true],"bearings":[60,150,240,330],"location":[-48.387415,-22.370145]},{"out":2,"in":0,"entry":[false,true,true,true],"bearings":[60,150,240,330],"location":[-48.388211,-22.370642]},{"out":2,"in":0,"entry":[false,true,true,true],"bearings":[60,150,240,330],"location":[-48.389011,-22.371128]},{"out":1,"in":0,"entry":[false,true,false],"bearings":[60,240,330],"location":[-48.389353,-22.371341]},{"out":1,"in":0,"entry":[false,true,true],"bearings":[60,225,285],"location":[-48.389573,-22.371475]},{"out":1,"in":0,"entry":[false,true],"bearings":[45,225],"location":[-48.389624,-22.371514]}],"weight":65.9,"duration":65.9,"distance":596.2},{"geometry":"~mpgCfcjfHFDp@p@d@l@dBdBzA|A","maneuver":{"bearing_after":220,"bearing_before":222,"location":[-48.389798,-22.371684],"modifier":"straight","type":"new name"},"mode":"driving","driving_side":"right","name":"Avenida Minas Gerais","intersections":[{"out":1,"in":0,"entry":[false,true],"bearings":[45,225],"location":[-48.389798,-22.371684]},{"out":2,"in":0,"entry":[false,true,true],"bearings":[45,135,225],"location":[-48.389829,-22.371716]},{"out":1,"in":0,"entry":[false,true,true],"bearings":[45,225,315],"location":[-48.390309,-22.372164]},{"out":1,"in":0,"entry":[false,true,true],"bearings":[45,225,330],"location":[-48.390819,-22.372665]}],"weight":29,"duration":29,"distance":222},{"geometry":"`wpgCpljfHNK","maneuver":{"bearing_after":142,"bearing_before":222,"location":[-48.391286,-22.373133],"modifier":"left","type":"end of road"},"mode":"driving","driving_side":"right","name":"Rua Sergipe","intersections":[{"out":1,"in":0,"entry":[false,true,true],"bearings":[45,150,300],"location":[-48.391286,-22.373133]}],"weight":0.7,"duration":0.7,"distance":10.4},{"geometry":"pwpgCdljfHLGLAN?VBJFRHfBr@jAd@PFJDp@VTHh@R|@ZbEzANDvGzBfDnAJL^Nl@RhFbBv@V~@Rp@JRDL@vAVBHFFHDF@F@BAFADEVGXGREVAp@Ej@Cd@Ad@Gf@GjAO~B]hAO~@OjAQbAQlAQh@GZGXCx@MtB]bAOn@Ij@GpAKf@@XDXHXLZTPN","maneuver":{"bearing_after":160,"bearing_before":142,"location":[-48.391225,-22.373208],"modifier":"slight right","type":"fork"},"mode":"driving","driving_side":"right","name":"Avenida Doutor Godofredo Schelini","intersections":[{"out":1,"in":2,"entry":[true,true,false],"bearings":[105,165,330],"location":[-48.391225,-22.373208]},{"out":0,"in":2,"entry":[true,true,false],"bearings":[180,240,345],"location":[-48.391175,-22.373348]},{"out":2,"in":0,"entry":[false,false,true],"bearings":[0,30,210],"location":[-48.391203,-22.373553]},{"out":2,"in":0,"entry":[false,true,true,true],"bearings":[30,135,210,315],"location":[-48.391293,-22.373708]},{"out":2,"in":0,"entry":[false,true,true],"bearings":[30,135,210],"location":[-48.391546,-22.374226]},{"out":2,"in":0,"entry":[false,true,true],"bearings":[30,135,195],"location":[-48.392714,-22.376703]},{"out":2,"in":0,"entry":[false,false,true],"bearings":[15,120,195],"location":[-48.39388,-22.379163]},{"out":2,"in":0,"entry":[false,true,true],"bearings":[15,120,195],"location":[-48.393977,-22.379388]},{"out":1,"in":0,"entry":[false,true,true],"bearings":[15,195,210],"location":[-48.394802,-22.381581]},{"out":2,"in":0,"entry":[false,false,true],"bearings":[15,90,240],"location":[-48.394924,-22.382019]},{"out":1,"in":0,"entry":[false,true,true],"bearings":[60,210,270],"location":[-48.394973,-22.382043]},{"out":1,"in":0,"entry":[false,true,false],"bearings":[30,180,315],"location":[-48.395055,-22.382205]},{"out":1,"in":0,"entry":[false,true,true],"bearings":[0,150,285],"location":[-48.395052,-22.382232]},{"out":1,"in":2,"entry":[true,true,false],"bearings":[105,165,330],"location":[-48.395013,-22.3823]},{"out":0,"in":1,"entry":[true,false],"bearings":[180,345],"location":[-48.394885,-22.382773]},{"out":0,"in":2,"entry":[true,true,false],"bearings":[165,240,345],"location":[-48.394437,-22.385207]},{"out":1,"in":3,"entry":[false,true,true,false],"bearings":[75,165,225,345],"location":[-48.39405,-22.386845]},{"out":1,"in":3,"entry":[true,true,false,false],"bearings":[75,165,285,345],"location":[-48.393987,-22.38712]}],"weight":129.7,"duration":129.7,"distance":1974.4},{"geometry":"t`tgCx|jfHNb@L`@Pl@Hb@Ln@z@fHrAbLJv@h@~DTbB^~Cd@bENzAHrADzABvA@xA?dAChAG`BE~@ShCc@nEu@pHUbCe@vEe@|E]|DOlBOzCMdDEjEBzCDxBHpBN~BP|BN`BL`ANhAPnAPz@Lp@^lB`@xB\\rBh@~BdChMtJbf@PbAVnAzAxH^jB~Ldn@|Gh]jD~PbArFd@xBr@lDXtAZbBvC~NfBpIXrATrAXrAp@~CJr@h@`CBJxDrSxGd]VrAB\\n@~GBz@DnAAZEpBo@zXGdCGnDE~CUlLQ~EO`C_@rCi@`C{@zC_AhC_ApB}A~CkRx_@wAnCuA~BoAjBkAzAaB~A}ApA{AfA_BbAiLnGyM|H{JpFaAh@{CfBgShKeH~DcRnK}HlEgTzL}MtHoFvCoIvEiH`EkCxAcB`AmBbAaCtA{@h@w@j@_An@w@n@eAz@cAz@}@v@_A~@iAjAgAlAo@r@}@pAwBpCoB`CqBhCiA|AkDtE}HbKuHzJwH`Ko@|@aBvBoCnD{AnB}@nAoA~AmA`BeC|CkA~A_CzCwBpC}ArBuAhB{ElG_DbE{DdFwBpCGJ_MbP_FpGUVWT]V[TUPUT]`@q@|@OROTMTKRM^Sb@OVS`@yFpH}FpHgLlOEDSPYVi@b@q@l@[\\e@l@e@l@QVY`@MXMTQ`@Sb@[h@QV}G|IiF~GcIjKoMxPiCdDkCjDyH~Jg@p@gDlEuAfBgB`CiDvE{@fAi@r@iAxA","maneuver":{"bearing_after":244,"bearing_before":213,"location":[-48.393892,-22.390034],"modifier":"straight","type":"turn"},"mode":"driving","ref":"SP-304","driving_side":"right","name":"Rodovia Deputado Amauri Barroso de Souza","intersections":[{"out":3,"in":0,"entry":[false,false,true,true],"bearings":[30,75,150,240],"location":[-48.393892,-22.390034]},{"out":2,"in":0,"entry":[false,false,true],"bearings":[75,90,255],"location":[-48.394888,-22.390392]},{"out":1,"in":0,"entry":[false,true,true],"bearings":[75,255,345],"location":[-48.396369,-22.390694]},{"out":2,"in":0,"entry":[false,true,true],"bearings":[75,165,255],"location":[-48.398746,-22.391172]},{"out":3,"in":1,"entry":[true,false,true,true],"bearings":[30,75,195,255],"location":[-48.399711,-22.391379]},{"out":2,"in":1,"entry":[true,false,true],"bearings":[75,105,285],"location":[-48.407478,-22.391656]},{"out":2,"in":0,"entry":[false,true,true],"bearings":[105,225,285],"location":[-48.409666,-22.391275]},{"out":1,"in":0,"entry":[false,true,true],"bearings":[75,255,270],"location":[-48.420412,-22.39099]},{"out":2,"in":0,"entry":[false,true,true],"bearings":[75,165,255],"location":[-48.421107,-22.391168]},{"out":2,"in":1,"entry":[false,false,true],"bearings":[30,75,255],"location":[-48.421361,-22.39124]},{"out":2,"in":0,"entry":[false,true,true],"bearings":[75,240,255],"location":[-48.432293,-22.39447]},{"out":2,"in":1,"entry":[true,false,true],"bearings":[45,75,255],"location":[-48.432628,-22.394562]},{"out":1,"in":0,"entry":[false,true,true],"bearings":[75,255,330],"location":[-48.435135,-22.395301]},{"out":3,"in":1,"entry":[true,false,true,true],"bearings":[0,75,180,255],"location":[-48.447543,-22.398965]},{"out":2,"in":0,"entry":[false,true,true,true],"bearings":[75,135,255,300],"location":[-48.456611,-22.401645]},{"out":1,"in":0,"entry":[false,true,true],"bearings":[75,255,270],"location":[-48.458298,-22.402165]},{"out":2,"in":0,"entry":[false,false,true],"bearings":[75,240,255],"location":[-48.458723,-22.402301]},{"out":2,"in":0,"entry":[false,false,true,false],"bearings":[75,165,255,330],"location":[-48.459142,-22.402407]},{"out":3,"in":1,"entry":[false,false,false,true],"bearings":[0,75,165,255],"location":[-48.459556,-22.402538]},{"out":2,"in":0,"entry":[false,false,true],"bearings":[72,76,255],"location":[-48.460363,-22.402787]},{"out":2,"in":1,"entry":[false,false,true],"bearings":[60,75,255],"location":[-48.460619,-22.40285]},{"out":2,"in":0,"entry":[false,true,true],"bearings":[75,135,255],"location":[-48.46127,-22.403063]},{"out":1,"in":0,"entry":[false,true,true],"bearings":[75,255,330],"location":[-48.461334,-22.403082]},{"out":2,"in":0,"entry":[false,true,true],"bearings":[75,165,255],"location":[-48.469876,-22.405535]},{"out":2,"in":1,"entry":[true,false,true],"bearings":[0,90,270],"location":[-48.471768,-22.40582]},{"out":2,"in":1,"entry":[true,false,true],"bearings":[0,90,270],"location":[-48.472306,-22.405839]},{"out":2,"in":0,"entry":[false,false,true,true],"bearings":[94,263,274,290],"location":[-48.477018,-22.405569]},{"out":3,"in":1,"entry":[false,false,false,true],"bearings":[0,90,195,270],"location":[-48.477686,-22.405526]},{"out":3,"in":1,"entry":[false,false,false,true],"bearings":[15,90,165,270],"location":[-48.47857,-22.405486]},{"out":3,"in":1,"entry":[false,false,false,true],"bearings":[75,90,105,270],"location":[-48.479367,-22.405457]},{"out":3,"in":1,"entry":[true,false,false,true],"bearings":[45,150,255,330],"location":[-48.50088,-22.39035]},{"out":3,"in":1,"entry":[false,false,false,true],"bearings":[75,150,225,330],"location":[-48.501091,-22.390024]},{"out":2,"in":1,"entry":[true,false,true],"bearings":[60,150,330],"location":[-48.504542,-22.384534]},{"out":2,"in":1,"entry":[true,false,true],"bearings":[60,150,330],"location":[-48.5146,-22.369019]},{"out":2,"in":1,"entry":[true,false,true],"bearings":[45,150,330],"location":[-48.515271,-22.367974]},{"out":2,"in":0,"entry":[false,true,true],"bearings":[135,225,315],"location":[-48.519976,-22.362937]},{"out":2,"in":1,"entry":[true,false,true],"bearings":[30,135,315],"location":[-48.524802,-22.358993]},{"out":2,"in":1,"entry":[true,false,true],"bearings":[90,135,315],"location":[-48.526697,-22.357444]},{"out":3,"in":1,"entry":[true,false,false,true],"bearings":[30,135,240,315],"location":[-48.528626,-22.355883]},{"out":3,"in":1,"entry":[false,false,true,true],"bearings":[45,135,195,315],"location":[-48.52894,-22.355635]},{"out":2,"in":0,"entry":[false,true,true],"bearings":[135,210,315],"location":[-48.54045,-22.346241]},{"out":3,"in":1,"entry":[true,false,true,true],"bearings":[45,135,240,315],"location":[-48.543245,-22.343957]},{"out":2,"in":0,"entry":[false,false,true],"bearings":[135,300,315],"location":[-48.544624,-22.342842]},{"out":2,"in":0,"entry":[false,false,true],"bearings":[150,225,315],"location":[-48.545172,-22.34221]},{"out":1,"in":0,"entry":[false,true,true],"bearings":[135,315,345],"location":[-48.545452,-22.341954]},{"out":2,"in":1,"entry":[false,false,true],"bearings":[90,135,315],"location":[-48.54576,-22.341703]},{"out":2,"in":0,"entry":[false,true,true],"bearings":[135,255,300],"location":[-48.546076,-22.34147]},{"out":2,"in":0,"entry":[false,false,true],"bearings":[120,135,315],"location":[-48.546814,-22.341056]},{"out":2,"in":0,"entry":[false,true,true],"bearings":[135,180,315],"location":[-48.552502,-22.336416]},{"out":2,"in":0,"entry":[false,false,true],"bearings":[135,300,315],"location":[-48.55253,-22.336393]},{"out":2,"in":0,"entry":[false,false,true],"bearings":[135,180,315],"location":[-48.553145,-22.335695]},{"out":1,"in":0,"entry":[false,true,true],"bearings":[135,315,330],"location":[-48.553303,-22.335557]},{"out":2,"in":1,"entry":[false,false,true],"bearings":[90,135,315],"location":[-48.553879,-22.335085]},{"out":2,"in":0,"entry":[false,true,true],"bearings":[135,255,300],"location":[-48.554048,-22.33496]},{"out":2,"in":0,"entry":[false,false,true],"bearings":[120,135,315],"location":[-48.55485,-22.334492]},{"out":2,"in":0,"entry":[false,true,true],"bearings":[135,225,315],"location":[-48.554966,-22.334401]},{"out":2,"in":0,"entry":[false,true,true],"bearings":[135,195,315],"location":[-48.55672,-22.332972]},{"out":2,"in":0,"entry":[false,true,true],"bearings":[135,210,315],"location":[-48.558156,-22.331798]},{"out":2,"in":0,"entry":[false,false,true],"bearings":[135,300,315],"location":[-48.570125,-22.322062]}],"weight":1079.999999999,"duration":1079.999999999,"distance":22678.5},{"geometry":"jrfgC~pmgHc@`@YXURQNQJSHUDYD]By@D]HSHMJILILINGPITM\\MVMVIHKLQJUJk@HgCZuBZ","maneuver":{"bearing_after":317,"bearing_before":310,"location":[-48.571202,-22.321177],"modifier":"slight right","type":"on ramp"},"mode":"driving","driving_side":"right","name":"","intersections":[{"out":2,"in":0,"entry":[false,true,true],"bearings":[135,300,315],"location":[-48.571202,-22.321177]}],"weight":41.6,"duration":41.6,"distance":522.8},{"geometry":"tyegC~~mgHaJr@q@FaDReEZqC^cCPcG`@sJx@{Ir@yBNaA@","maneuver":{"bearing_after":351,"bearing_before":345,"location":[-48.573444,-22.317231],"modifier":"slight left","type":"merge"},"mode":"driving","ref":"SP-255; SP-304","driving_side":"right","name":"Contorno Rodoviário Antônio Prado Galvão de Barros","intersections":[{"out":2,"in":0,"entry":[false,false,true],"bearings":[165,180,345],"location":[-48.573444,-22.317231]},{"out":2,"in":1,"entry":[true,false,true],"bearings":[0,165,345],"location":[-48.573982,-22.313407]},{"out":0,"in":1,"entry":[true,false,false],"bearings":[0,165,180],"location":[-48.575033,-22.306513]}],"weight":49.5,"duration":49.5,"distance":1235.6},{"geometry":"rtcgC~hngHgENqBBe@@kDXa@@a@C[E","maneuver":{"bearing_after":355,"bearing_before":357,"location":[-48.575043,-22.306176],"modifier":"slight right","type":"off ramp"},"mode":"driving","driving_side":"right","name":"","intersections":[{"out":0,"in":1,"entry":[true,false,true],"bearings":[0,180,345],"location":[-48.575043,-22.306176]}],"weight":27.5,"duration":27.5,"distance":344.7},{"geometry":"facgCfjngH[S[I[C]BYDa@NKJMNM\\CTAT@XBTHPP\\TN","maneuver":{"exit":3,"bearing_after":33,"bearing_before":7,"location":[-48.575242,-22.303077],"modifier":"slight right","type":"roundabout"},"mode":"driving","ref":"SP-225; BR-369","driving_side":"right","name":"Rodovia Comandante João Ribeiro de Barros","intersections":[{"out":0,"in":1,"entry":[true,false,false],"bearings":[30,195,225],"location":[-48.575242,-22.303077]},{"out":0,"in":2,"entry":[true,true,false],"bearings":[15,45,210],"location":[-48.575143,-22.302942]},{"out":2,"in":1,"entry":[false,false,true],"bearings":[120,150,315],"location":[-48.575198,-22.30221]},{"out":1,"in":0,"entry":[false,true,true],"bearings":[135,300,330],"location":[-48.575338,-22.302081]},{"out":2,"in":1,"entry":[false,false,true],"bearings":[15,60,225],"location":[-48.576187,-22.302154]}],"weight":9.399999999,"duration":9.399999999,"distance":231.5},{"geometry":"b|bgCtpngH`@l@Zx@F\\B`@Bf@\\tMp@b[JxB`@jHxAto@N`JRhHXnF^xOLrFL~EFbCHjElB|x@t@r\\L~FBvAx@d]\\rNbEnjBZpMZvNFfBZrNd@bTX~Ld@|RJrEJvEJtEZdN\\lN\\|Oj@|U^zO@^TpKTlHJfGF|IHhFFxBZzMl@|W`@pKPlFLxDFzBf@|Ux@x\\\\jHh@pGjApIhAbHR`Aj@bC|AlGr@zBnC~Hf@xAnAtCnAhCnAfC`@r@rA~BlCdEzBbDtB`DxB|CvAjBHLHLzEfHhD~EpI~LlFnIpBfD`A~AtAjCtCtGxCjHjBdFjApDrAtEl@dCvAvGxAfIv@dJFp@z@hJ\\nDd@xEz@xIZlDjAfMt@tHn@zGT~B`@xEZ|CJ~@TdCxFtl@tBzRp@dHp@pHHx@lAbMpCzZnClYtAlNj@fGN`CVbDf@tFbAjKtBbU^tDLvA\\nFd@rFd@`Fp@bHH~@n@fIJ`AjCpXdCdXdE`c@dAbLLvAt@|Hr@zHlAtMp@nLF`AV~ERzEZhIX~MFbJ?hMOzP_@zR_ApSu@fMcA|Ls@jHWfCiAvK}CdZ_DjZ{CxYMtAgC`VoCzWmAvL[bDi@fFwCxXsBxRi@`FcCbVmAnLmAdLcCxUgCnVcCnUgBbQCVa@|DqB`RwBtSkApKuA`Nc@tFKz@q@bHKdAs@xGgAbJOxAq@`HiDl[_@dDwBvRyDb_@oObyAcEz`@yA|M?\\aEtb@Gn@g@rEmChVcFvf@o@~Gg@nE","maneuver":{"exit":3,"bearing_after":230,"bearing_before":216,"location":[-48.576272,-22.302256],"modifier":"straight","type":"exit roundabout"},"mode":"driving","ref":"SP-225; BR-369","driving_side":"right","name":"Rodovia Comandante João Ribeiro de Barros","intersections":[{"out":2,"in":0,"entry":[false,true,true],"bearings":[45,210,225],"location":[-48.576272,-22.302256]},{"out":1,"in":0,"entry":[false,true,true],"bearings":[84,263,271],"location":[-48.584769,-22.303108]},{"out":2,"in":1,"entry":[false,false,true],"bearings":[75,90,270],"location":[-48.597318,-22.30391]},{"out":1,"in":0,"entry":[false,true,true],"bearings":[86,267,271],"location":[-48.60121,-22.304197]},{"out":2,"in":1,"entry":[false,false,true],"bearings":[75,90,270],"location":[-48.604207,-22.304376]},{"out":1,"in":0,"entry":[false,true,true],"bearings":[86,267,271],"location":[-48.614503,-22.304981]},{"out":2,"in":0,"entry":[false,false,true],"bearings":[84,87,266],"location":[-48.620957,-22.305342]},{"out":1,"in":0,"entry":[false,true,true],"bearings":[90,270,285],"location":[-48.625788,-22.305633]},{"out":2,"in":1,"entry":[false,false,true],"bearings":[75,90,270],"location":[-48.628291,-22.305777]},{"out":1,"in":0,"entry":[false,true,true],"bearings":[86,267,276],"location":[-48.647824,-22.3069]},{"out":2,"in":1,"entry":[false,false,true],"bearings":[75,90,270],"location":[-48.650339,-22.307039]},{"out":1,"in":0,"entry":[false,true,true],"bearings":[90,270,345],"location":[-48.67936,-22.308729]},{"out":1,"in":0,"entry":[false,true,true],"bearings":[90,270,285],"location":[-48.687886,-22.30915]},{"out":2,"in":1,"entry":[false,false,true],"bearings":[75,90,270],"location":[-48.696267,-22.309691]},{"out":1,"in":0,"entry":[false,true,true],"bearings":[75,255,285],"location":[-48.714463,-22.311808]},{"out":2,"in":1,"entry":[false,false,true],"bearings":[45,60,240],"location":[-48.716429,-22.312538]},{"out":1,"in":0,"entry":[false,true,true],"bearings":[60,240,255],"location":[-48.738169,-22.326541]},{"out":2,"in":1,"entry":[false,false,true],"bearings":[54,67,250],"location":[-48.740134,-22.327339]},{"out":1,"in":0,"entry":[false,true,true],"bearings":[75,255,345],"location":[-48.74857,-22.329234]},{"out":1,"in":0,"entry":[false,true,true],"bearings":[75,255,345],"location":[-48.754536,-22.330235]},{"out":2,"in":1,"entry":[false,false,true],"bearings":[60,75,255],"location":[-48.759241,-22.331032]},{"out":1,"in":0,"entry":[false,true,true],"bearings":[75,255,270],"location":[-48.761022,-22.331338]},{"out":1,"in":0,"entry":[false,true,true],"bearings":[75,255,270],"location":[-48.77151,-22.33318]},{"out":2,"in":1,"entry":[false,false,true],"bearings":[45,75,255],"location":[-48.772984,-22.333426]},{"out":1,"in":0,"entry":[false,true,true],"bearings":[75,255,270],"location":[-48.792237,-22.336617]},{"out":2,"in":1,"entry":[false,false,true],"bearings":[69,80,260],"location":[-48.798667,-22.337709]},{"out":1,"in":0,"entry":[false,true,true],"bearings":[75,255,270],"location":[-48.801534,-22.338124]},{"out":2,"in":1,"entry":[false,false,true],"bearings":[60,75,255],"location":[-48.806081,-22.338849]},{"out":1,"in":0,"entry":[false,true,true],"bearings":[80,263,273],"location":[-48.828361,-22.342607]},{"out":2,"in":1,"entry":[false,false,true],"bearings":[75,90,270],"location":[-48.833073,-22.343118]},{"out":1,"in":0,"entry":[false,true,true],"bearings":[105,285,300],"location":[-48.856528,-22.341997]},{"out":2,"in":1,"entry":[false,false,true],"bearings":[90,105,285],"location":[-48.857213,-22.341875]},{"out":1,"in":0,"entry":[false,true,true],"bearings":[105,285,345],"location":[-48.872697,-22.339069]},{"out":1,"in":0,"entry":[false,true,true],"bearings":[105,285,300],"location":[-48.882568,-22.337281]},{"out":2,"in":1,"entry":[false,false,true],"bearings":[75,105,285],"location":[-48.883389,-22.337136]},{"out":1,"in":0,"entry":[false,true,true],"bearings":[105,285,345],"location":[-48.891847,-22.335592]},{"out":1,"in":0,"entry":[false,true,true],"bearings":[101,281,285],"location":[-48.896675,-22.334718]},{"out":2,"in":1,"entry":[false,false,true],"bearings":[90,105,285],"location":[-48.904601,-22.333279]},{"out":2,"in":1,"entry":[true,false,true],"bearings":[15,105,285],"location":[-48.928239,-22.329011]},{"out":2,"in":1,"entry":[true,false,true],"bearings":[15,105,285],"location":[-48.933691,-22.328004]},{"out":2,"in":1,"entry":[true,false,true],"bearings":[15,105,285],"location":[-48.94052,-22.326744]},{"out":1,"in":0,"entry":[false,true,true],"bearings":[102,281,289],"location":[-48.943683,-22.326136]},{"out":2,"in":1,"entry":[false,false,true],"bearings":[90,105,285],"location":[-48.948824,-22.325209]},{"out":1,"in":0,"entry":[false,true,true],"bearings":[101,278,284],"location":[-48.971049,-22.321142]},{"out":2,"in":1,"entry":[false,false,true],"bearings":[90,105,285],"location":[-48.988297,-22.318078]}],"weight":1812.8,"duration":1812.8,"distance":43726.9},{"geometry":"f|egCjo_jHu@~EMt@Wr@s@hAgM~NoD`E","maneuver":{"bearing_after":284,"bearing_before":281,"location":[-48.990776,-22.317642],"modifier":"slight right","type":"off ramp"},"mode":"driving","destinations":"Bauru","driving_side":"right","name":"","intersections":[{"out":2,"in":0,"entry":[false,true,true],"bearings":[101,281,285],"location":[-48.990776,-22.317642]}],"weight":58.4,"duration":58.4,"distance":730.3},{"geometry":"~cegC`r`jHmB|B[^iBtBqB~BqCdDuBbCmC~C{@r@c@X_@P[Lc@T","maneuver":{"bearing_after":312,"bearing_before":313,"location":[-48.996325,-22.313763],"modifier":"straight","type":"turn"},"mode":"driving","driving_side":"right","name":"Avenida Rodrigues Alves","intersections":[{"out":2,"in":0,"entry":[false,false,true],"bearings":[135,150,315],"location":[-48.996325,-22.313763]},{"out":2,"in":1,"entry":[true,false,true],"bearings":[0,135,315],"location":[-48.996963,-22.313207]},{"out":2,"in":1,"entry":[false,false,true],"bearings":[15,135,315],"location":[-48.997116,-22.313065]}],"weight":48.5,"duration":48.5,"distance":740.5},{"geometry":"bfdgCbqajHMDE@YT]\\OTKRAP","maneuver":{"exit":2,"bearing_after":341,"bearing_before":329,"location":[-49.001304,-22.308983],"modifier":"straight","type":"rotary"},"mode":"driving","driving_side":"right","name":"Avenida Rodrigues Alves","intersections":[{"out":2,"in":0,"entry":[false,false,true],"bearings":[150,180,345],"location":[-49.001304,-22.308983]},{"out":2,"in":1,"entry":[true,false,true],"bearings":[15,165,330],"location":[-49.001341,-22.30888]},{"out":2,"in":1,"entry":[false,false,true],"bearings":[90,120,285],"location":[-49.001812,-22.308458]}],"rotary_name":"Avenida Rodrigues Alves","weight":5.8,"duration":5.8,"distance":89.3},{"geometry":"xbdgCztajHQn@Sl@[r@a@n@e@l@m@`Ae@`A]~@WdAQjAK~@E~@AnABjAFv@R`BX`B`@hCXhBVbB`@hCn@hEhEpXtA|I|A|Jh@fDxBfNB^@\\AzBGzBBd@Hb@ZdAl@tAh@hAPd@Jf@~@hGLx@nDjUJj@`AnGPp@LdADj@Bh@Bj@?R@r@","maneuver":{"exit":2,"bearing_after":291,"bearing_before":278,"location":[-49.001901,-22.308445],"modifier":"straight","type":"exit rotary"},"mode":"driving","driving_side":"right","name":"Avenida Rodrigues Alves","intersections":[{"out":2,"in":0,"entry":[false,true,true],"bearings":[105,270,285],"location":[-49.001901,-22.308445]},{"out":1,"in":0,"entry":[false,true,true],"bearings":[75,255,270],"location":[-49.018658,-22.30991]},{"out":2,"in":1,"entry":[false,false,true],"bearings":[60,75,255],"location":[-49.019496,-22.310118]},{"out":2,"in":0,"entry":[false,false,true],"bearings":[90,105,270],"location":[-49.022871,-22.310745]},{"out":2,"in":0,"entry":[false,true,true],"bearings":[60,210,240],"location":[-49.024637,-22.311149]}],"weight":224.799999999,"duration":224.799999999,"distance":3433.8},{"geometry":"xaegCd|gjHEP?PBLFL","maneuver":{"exit":1,"bearing_after":289,"bearing_before":265,"location":[-49.033788,-22.313411],"modifier":"slight right","type":"roundabout"},"mode":"driving","driving_side":"right","name":"Avenida Rodrigues Alves","intersections":[{"out":2,"in":0,"entry":[false,false,true],"bearings":[90,120,285],"location":[-49.033788,-22.313411]},{"out":2,"in":1,"entry":[false,false,true],"bearings":[60,90,255],"location":[-49.033967,-22.313382]},{"out":2,"in":1,"entry":[true,false,true],"bearings":[15,75,240],"location":[-49.034044,-22.313401]}],"weight":2.2,"duration":2.2,"distance":35.4},{"geometry":"~aegCd~gjHVn@n@fBV~@v@dFz@dFT|ARnAr@vDfAvGz@bGDZVxAj@lDn@lEn@rEj@fDJd@r@lEXnBRzAt@pEp@nEd@rCLt@d@zCF\\^bChAhHd@`DLbAx@vE\\|BNbAVrAVhBz@zFh@hD~AtJ@Nj@hDh@fDf@fDf@hDVdBDZn@tDn@fE","maneuver":{"exit":1,"bearing_after":241,"bearing_before":239,"location":[-49.034113,-22.313439],"modifier":"straight","type":"exit roundabout"},"mode":"driving","driving_side":"right","name":"Avenida Rodrigues Alves","intersections":[{"out":2,"in":0,"entry":[false,true,true],"bearings":[60,225,240],"location":[-49.034113,-22.313439]},{"out":2,"in":0,"entry":[false,true,true],"bearings":[75,165,255],"location":[-49.037957,-22.314609]},{"out":3,"in":1,"entry":[true,false,true,true],"bearings":[60,75,165,255],"location":[-49.042118,-22.31566]},{"out":2,"in":0,"entry":[false,true,true],"bearings":[75,165,255],"location":[-49.042573,-22.315777]},{"out":2,"in":0,"entry":[false,true,true,true],"bearings":[75,165,255,345],"location":[-49.043442,-22.316]},{"out":2,"in":0,"entry":[false,true,true,true],"bearings":[75,165,255,345],"location":[-49.045534,-22.316484]},{"out":2,"in":0,"entry":[false,true,true,true],"bearings":[75,165,255,345],"location":[-49.046559,-22.316757]},{"out":2,"in":0,"entry":[false,true,true,true],"bearings":[75,165,255,345],"location":[-49.047593,-22.317021]},{"out":2,"in":0,"entry":[false,true,true,true],"bearings":[75,165,255,345],"location":[-49.048606,-22.317251]},{"out":2,"in":0,"entry":[false,true,true,true],"bearings":[75,165,255,345],"location":[-49.04966,-22.317518]},{"out":2,"in":0,"entry":[false,true,true],"bearings":[75,165,255],"location":[-49.050698,-22.317772]},{"out":2,"in":0,"entry":[false,true,true],"bearings":[75,165,255],"location":[-49.051707,-22.318031]},{"out":1,"in":0,"entry":[false,true,true],"bearings":[75,255,345],"location":[-49.052494,-22.31822]},{"out":2,"in":0,"entry":[false,true,true,false],"bearings":[75,195,255,345],"location":[-49.05264,-22.318261]},{"out":2,"in":0,"entry":[false,true,true,true],"bearings":[75,165,255,345],"location":[-49.055602,-22.318982]},{"out":1,"in":0,"entry":[false,true,true],"bearings":[75,255,285],"location":[-49.055937,-22.319054]},{"out":3,"in":1,"entry":[false,false,true,true],"bearings":[15,75,210,255],"location":[-49.057023,-22.319343]},{"out":3,"in":1,"entry":[true,false,true,true],"bearings":[0,75,180,255],"location":[-49.057992,-22.319571]},{"out":2,"in":0,"entry":[false,true,true],"bearings":[75,165,255],"location":[-49.058413,-22.319688]},{"out":3,"in":1,"entry":[true,false,true,true],"bearings":[15,75,210,255],"location":[-49.058939,-22.319813]},{"out":2,"in":0,"entry":[false,true,true,false],"bearings":[75,120,255,345],"location":[-49.060202,-22.320114]},{"out":2,"in":0,"entry":[false,false,true,true],"bearings":[75,180,255,345],"location":[-49.061047,-22.320324]},{"out":2,"in":0,"entry":[false,false,true,true],"bearings":[75,165,255,345],"location":[-49.062924,-22.320798]},{"out":2,"in":0,"entry":[false,true,true,false],"bearings":[75,165,255,345],"location":[-49.063004,-22.320814]},{"out":2,"in":0,"entry":[false,false,true,true],"bearings":[75,165,255,345],"location":[-49.063854,-22.321027]},{"out":2,"in":0,"entry":[false,true,true,false],"bearings":[75,165,255,345],"location":[-49.064687,-22.321235]},{"out":2,"in":0,"entry":[false,false,true],"bearings":[75,165,255],"location":[-49.066377,-22.321642]},{"out":2,"in":0,"entry":[false,false,true,true],"bearings":[75,150,255,315],"location":[-49.066886,-22.321759]},{"out":2,"in":0,"entry":[false,true,true,false],"bearings":[75,135,255,315],"location":[-49.067033,-22.321793]},{"out":2,"in":0,"entry":[false,true,true,false],"bearings":[75,165,255,345],"location":[-49.067937,-22.322027]}],"weight":301.5,"duration":301.5,"distance":3720.9},{"geometry":"dyfgCzwnjHcBXqDr@","maneuver":{"bearing_after":345,"bearing_before":254,"location":[-49.068936,-22.322265],"modifier":"right","type":"turn"},"mode":"driving","driving_side":"right","name":"Rua Araújo Leite","intersections":[{"out":3,"in":0,"entry":[false,false,true,true],"bearings":[75,165,255,345],"location":[-49.068936,-22.322265]},{"out":3,"in":1,"entry":[true,false,false,true],"bearings":[75,165,255,345],"location":[-49.069069,-22.321771]}],"weight":28.2,"duration":28.2,"distance":159.1},{"geometry":"npfgChznjHl@bE","maneuver":{"bearing_after":254,"bearing_before":344,"location":[-49.069329,-22.320876],"modifier":"left","type":"turn"},"mode":"driving","driving_side":"right","name":"Rua Primeiro de Agosto","intersections":[{"out":2,"in":1,"entry":[false,false,true,true],"bearings":[75,165,255,345],"location":[-49.069329,-22.320876]}],"weight":20.4,"duration":20.4,"distance":104.5},{"geometry":"|qfgCl`ojHvB_@","maneuver":{"bearing_after":165,"bearing_before":254,"location":[-49.070312,-22.32111],"modifier":"left","type":"turn"},"mode":"driving","driving_side":"right","name":"Rua Antônio Alves","intersections":[{"out":1,"in":0,"entry":[false,true,true,false],"bearings":[75,165,255,345],"location":[-49.070312,-22.32111]}],"weight":9.8,"duration":9.8,"distance":68.6},{"geometry":"tufgCl_ojH","maneuver":{"bearing_after":0,"bearing_before":166,"location":[-49.070153,-22.321712],"modifier":"right","type":"arrive"},"mode":"driving","driving_side":"right","name":"Rua Antônio Alves","intersections":[{"in":0,"entry":[true],"bearings":[346],"location":[-49.070153,-22.321712]}],"weight":0,"duration":0,"distance":0}],"summary":"Rodovia Deputado Amauri Barroso de Souza, Rodovia Comandante João Ribeiro de Barros","weight":3962.3,"duration":3962.3,"distance":80755.2}],"weight_name":"routability","weight":3962.3,"duration":3962.3,"distance":80755.2},{"geometry":"bapgC~`ifHu@d@kCdB`BzCbB~CdBbD`B|C`B~Ch@bAZj@DH`@b@FDp@p@d@l@dBdBzA|ANKLGLAN?VBJFRHfBr@jAd@PFJDp@VTHh@R|@ZbEzANDvGzBfDnAJL^Nl@RhFbBv@V~@Rp@JRDL@vAVBHFFHDF@F@BAFADEVGXGREVAp@Ej@Cd@Ad@Gf@GjAO~B]hAO~@OjAQbAQlAQh@GZGXCx@MtB]bAOn@Ij@GpAKf@@XDXHXLZTPNNb@L`@Pl@Hb@Ln@z@fHrAbLJv@h@~DTbB^~Cd@bENzAHrADzABvA@xA?dAChAG`BE~@ShCc@nEu@pHUbCe@vEe@|E]|DOlBOzCMdDEjEBzCDxBHpBN~BP|BN`BL`ANhAPnAPz@Lp@^lB`@xB\\rBh@~BdChMtJbf@PbAVnAzAxH^jB~Ldn@|Gh]jD~PbArFd@xBr@lDXtAZbBvC~NfBpIXrATrAXrAp@~CJr@h@`CBJxDrSxGd]VrAB\\n@~GBz@DnAAZEpBo@zXGdCGnDE~CUlLQ~EO`C_@rCi@`C{@zC_AhC_ApB}A~CkRx_@wAnCuA~BoAjBkAzAaB~A}ApA{AfA_BbAiLnGyM|H{JpFaAh@{CfBgShKeH~DcRnK}HlEgTzL}MtHoFvCoIvEiH`EkCxAcB`AmBbAaCtA{@h@w@j@_An@w@n@eAz@cAz@}@v@_A~@iAjAgAlAo@r@}@pAwBpCoB`CqBhCiA|AkDtE}HbKuHzJwH`Ko@|@aBvBoCnD{AnB}@nAoA~AmA`BeC|CkA~A_CzCwBpC}ArBuAhB{ElG_DbE{DdFwBpCGJ_MbP_FpGUVWT]V[TUPUT]`@q@|@OROTMTKRM^Sb@OVS`@yFpH}FpHgLlOEDSPYVi@b@q@l@[\\e@l@e@l@QVY`@MXMTQ`@Sb@[h@QV}G|IiF~GcIjKoMxPiCdDkCjDyH~Jg@p@gDlEuAfBgB`CiDvE{@fAi@r@iAxAc@`@YXURQNQJSHUDYD]By@D]HSHMJILILINGPITM\\MVMVIHKLQJUJk@HgCZuBZaJr@q@FaDReEZqC^cCPcG`@sJx@{Ir@yBNaA@gENqBBe@@kDXa@@a@C[E[S[I[C]BYDa@NKJMNM\\CTAT@XBTHPP\\TN`@l@Zx@F\\B`@Bf@\\tMp@b[JxB`@jHxAto@N`JRhHXnF^xOLrFL~EFbCHjElB|x@t@r\\L~FBvAx@d]\\rNbEnjBZpMZvNFfBZrNd@bTX~Ld@|RJrEJvEJtEZdN\\lN\\|Oj@|U^zO@^TpKTlHJfGF|IHhFFxBZzMl@|W`@pKPlFLxDFzBf@|Ux@x\\\\jHh@pGjApIhAbHR`Aj@bC|AlGr@zBnC~Hf@xAnAtCnAhCnAfC`@r@rA~BlCdEzBbDtB`DxB|CvAjBHLHLzEfHhD~EpI~LlFnIpBfD`A~AtAjCtCtGxCjHjBdFjApDrAtEl@dCvAvGxAfIv@dJFp@z@hJ\\nDd@xEz@xIZlDjAfMt@tHn@zGT~B`@xEZ|CJ~@TdCxFtl@tBzRp@dHp@pHHx@lAbMpCzZnClYtAlNj@fGN`CVbDf@tFbAjKtBbU^tDLvA\\nFd@rFd@`Fp@bHH~@n@fIJ`AjCpXdCdXdE`c@dAbLLvAt@|Hr@zHlAtMp@nLF`AV~ERzEZhIX~MFbJ?hMOzP_@zR_ApSu@fMcA|Ls@jHWfCiAvK}CdZ_DjZ{CxYMtAgC`VoCzWmAvL[bDi@fFwCxXsBxRi@`FcCbVmAnLmAdLcCxUgCnVcCnUgBbQCVa@|DqB`RwBtSkApKuA`Nc@tFKz@q@bHKdAs@xGgAbJOxAq@`HiDl[_@dDwBvRyDb_@oObyAcEz`@yA|M?\\aEtb@Gn@g@rEmChVcFvf@o@~Gg@nEg@tE{@`Je@|EUtBg@dF[tCOdBKxC@j@Bl@HdA\\jBh@jBd@hAh@hA`ArAbC~BpB`BvBfBvE~DxItHlEtD`DlClB~AfBzAvD~CfCzBx@p@|F`FxE|DnGlF|EdErFxEjFnEnErD|GnFhAhA~M~KlKvInAfAvHrGxFhFdH`GrCfClMjKxMdLTH`NlLtIrHbEnDnAbCxBlBJJnCzBlDhC`@^~@bA`@d@R`@L^D^Bj@Af@Mn@Oh@c@p@g@^w@Zg@Hs@LcDr@]HaAR[BY@u@O[GYGWE_@Ai@DcAP_@FIBUJ[Ne@f@s@`A_B~@}Ad@u@P{Cr@eCh@yDr@gGlA{HbBa@H_LtBgBb@kStDyGxAe@JcCd@{@NoARaB\\q@JoG|AiQrDmE|@gGhAwDr@mDt@kDt@qDp@iDp@aAXq@NgF~@_Dh@MB@T@`B?T\\zDf@|D\\~D\\|Dd@~DB\\H`@`@|Cp@xDl@zDVlBFrADx@Ad@Eb@K`@O^QZMLKR_@TuBpBg@`@a@\\gA`AuCtCu@p@cBxA{ChC_@ZkDxCQLDZn@tDn@fEcBXqDr@l@bEvB_@","legs":[{"steps":[{"geometry":"bapgC~`ifHu@d@kCdB","maneuver":{"bearing_after":326,"bearing_before":0,"location":[-48.384315,-22.369623],"modifier":"left","type":"depart"},"mode":"driving","driving_side":"right","name":"Avenida José Alves Mira","intersections":[{"out":0,"entry":[true],"bearings":[326],"location":[-48.384315,-22.369623]},{"out":3,"in":1,"entry":[true,false,false,true],"bearings":[60,150,240,330],"location":[-48.384509,-22.369351]}],"weight":16.6,"duration":16.6,"distance":129.6},{"geometry":"`{ogCjeifH`BzCbB~CdBbD`B|C`B~Ch@bAZj@DH`@b@","maneuver":{"bearing_after":234,"bearing_before":324,"location":[-48.38502,-22.368654],"modifier":"left","type":"turn"},"mode":"driving","driving_side":"right","name":"Rua Treze de Maio","intersections":[{"out":2,"in":1,"entry":[false,false,true,true],"bearings":[60,150,240,330],"location":[-48.38502,-22.368654]},{"out":2,"in":0,"entry":[false,true,true,true],"bearings":[60,150,240,330],"location":[-48.385801,-22.369144]},{"out":2,"in":0,"entry":[false,true,true,true],"bearings":[60,150,240,330],"location":[-48.3866,-22.369635]},{"out":2,"in":0,"entry":[false,true,true,true],"bearings":[60,150,240,330],"location":[-48.387415,-22.370145]},{"out":2,"in":0,"entry":[false,true,true,true],"bearings":[60,150,240,330],"location":[-48.388211,-22.370642]},{"out":2,"in":0,"entry":[false,true,true,true],"bearings":[60,150,240,330],"location":[-48.389011,-22.371128]},{"out":1,"in":0,"entry":[false,true,false],"bearings":[60,240,330],"location":[-48.389353,-22.371341]},{"out":1,"in":0,"entry":[false,true,true],"bearings":[60,225,285],"location":[-48.389573,-22.371475]},{"out":1,"in":0,"entry":[false,true],"bearings":[45,225],"location":[-48.389624,-22.371514]}],"weight":65.9,"duration":65.9,"distance":596.2},{"geometry":"~mpgCfcjfHFDp@p@d@l@dBdBzA|A","maneuver":{"bearing_after":220,"bearing_before":222,"location":[-48.389798,-22.371684],"modifier":"straight","type":"new name"},"mode":"driving","driving_side":"right","name":"Avenida Minas Gerais","intersections":[{"out":1,"in":0,"entry":[false,true],"bearings":[45,225],"location":[-48.389798,-22.371684]},{"out":2,"in":0,"entry":[false,true,true],"bearings":[45,135,225],"location":[-48.389829,-22.371716]},{"out":1,"in":0,"entry":[false,true,true],"bearings":[45,225,315],"location":[-48.390309,-22.372164]},{"out":1,"in":0,"entry":[false,true,true],"bearings":[45,225,330],"location":[-48.390819,-22.372665]}],"weight":29,"duration":29,"distance":222},{"geometry":"`wpgCpljfHNK","maneuver":{"bearing_after":142,"bearing_before":222,"location":[-48.391286,-22.373133],"modifier":"left","type":"end of road"},"mode":"driving","driving_side":"right","name":"Rua Sergipe","intersections":[{"out":1,"in":0,"entry":[false,true,true],"bearings":[45,150,300],"location":[-48.391286,-22.373133]}],"weight":0.7,"duration":0.7,"distance":10.4},{"geometry":"pwpgCdljfHLGLAN?VBJFRHfBr@jAd@PFJDp@VTHh@R|@ZbEzANDvGzBfDnAJL^Nl@RhFbBv@V~@Rp@JRDL@vAVBHFFHDF@F@BAFADEVGXGREVAp@Ej@Cd@Ad@Gf@GjAO~B]hAO~@OjAQbAQlAQh@GZGXCx@MtB]bAOn@Ij@GpAKf@@XDXHXLZTPN","maneuver":{"bearing_after":160,"bearing_before":142,"location":[-48.391225,-22.373208],"modifier":"slight right","type":"fork"},"mode":"driving","driving_side":"right","name":"Avenida Doutor Godofredo Schelini","intersections":[{"out":1,"in":2,"entry":[true,true,false],"bearings":[105,165,330],"location":[-48.391225,-22.373208]},{"out":0,"in":2,"entry":[true,true,false],"bearings":[180,240,345],"location":[-48.391175,-22.373348]},{"out":2,"in":0,"entry":[false,false,true],"bearings":[0,30,210],"location":[-48.391203,-22.373553]},{"out":2,"in":0,"entry":[false,true,true,true],"bearings":[30,135,210,315],"location":[-48.391293,-22.373708]},{"out":2,"in":0,"entry":[false,true,true],"bearings":[30,135,210],"location":[-48.391546,-22.374226]},{"out":2,"in":0,"entry":[false,true,true],"bearings":[30,135,195],"location":[-48.392714,-22.376703]},{"out":2,"in":0,"entry":[false,false,true],"bearings":[15,120,195],"location":[-48.39388,-22.379163]},{"out":2,"in":0,"entry":[false,true,true],"bearings":[15,120,195],"location":[-48.393977,-22.379388]},{"out":1,"in":0,"entry":[false,true,true],"bearings":[15,195,210],"location":[-48.394802,-22.381581]},{"out":2,"in":0,"entry":[false,false,true],"bearings":[15,90,240],"location":[-48.394924,-22.382019]},{"out":1,"in":0,"entry":[false,true,true],"bearings":[60,210,270],"location":[-48.394973,-22.382043]},{"out":1,"in":0,"entry":[false,true,false],"bearings":[30,180,315],"location":[-48.395055,-22.382205]},{"out":1,"in":0,"entry":[false,true,true],"bearings":[0,150,285],"location":[-48.395052,-22.382232]},{"out":1,"in":2,"entry":[true,true,false],"bearings":[105,165,330],"location":[-48.395013,-22.3823]},{"out":0,"in":1,"entry":[true,false],"bearings":[180,345],"location":[-48.394885,-22.382773]},{"out":0,"in":2,"entry":[true,true,false],"bearings":[165,240,345],"location":[-48.394437,-22.385207]},{"out":1,"in":3,"entry":[false,true,true,false],"bearings":[75,165,225,345],"location":[-48.39405,-22.386845]},{"out":1,"in":3,"entry":[true,true,false,false],"bearings":[75,165,285,345],"location":[-48.393987,-22.38712]}],"weight":129.7,"duration":129.7,"distance":1974.4},{"geometry":"t`tgCx|jfHNb@L`@Pl@Hb@Ln@z@fHrAbLJv@h@~DTbB^~Cd@bENzAHrADzABvA@xA?dAChAG`BE~@ShCc@nEu@pHUbCe@vEe@|E]|DOlBOzCMdDEjEBzCDxBHpBN~BP|BN`BL`ANhAPnAPz@Lp@^lB`@xB\\rBh@~BdChMtJbf@PbAVnAzAxH^jB~Ldn@|Gh]jD~PbArFd@xBr@lDXtAZbBvC~NfBpIXrATrAXrAp@~CJr@h@`CBJxDrSxGd]VrAB\\n@~GBz@DnAAZEpBo@zXGdCGnDE~CUlLQ~EO`C_@rCi@`C{@zC_AhC_ApB}A~CkRx_@wAnCuA~BoAjBkAzAaB~A}ApA{AfA_BbAiLnGyM|H{JpFaAh@{CfBgShKeH~DcRnK}HlEgTzL}MtHoFvCoIvEiH`EkCxAcB`AmBbAaCtA{@h@w@j@_An@w@n@eAz@cAz@}@v@_A~@iAjAgAlAo@r@}@pAwBpCoB`CqBhCiA|AkDtE}HbKuHzJwH`Ko@|@aBvBoCnD{AnB}@nAoA~AmA`BeC|CkA~A_CzCwBpC}ArBuAhB{ElG_DbE{DdFwBpCGJ_MbP_FpGUVWT]V[TUPUT]`@q@|@OROTMTKRM^Sb@OVS`@yFpH}FpHgLlOEDSPYVi@b@q@l@[\\e@l@e@l@QVY`@MXMTQ`@Sb@[h@QV}G|IiF~GcIjKoMxPiCdDkCjDyH~Jg@p@gDlEuAfBgB`CiDvE{@fAi@r@iAxA","maneuver":{"bearing_after":244,"bearing_before":213,"location":[-48.393892,-22.390034],"modifier":"straight","type":"turn"},"mode":"driving","ref":"SP-304","driving_side":"right","name":"Rodovia Deputado Amauri Barroso de Souza","intersections":[{"out":3,"in":0,"entry":[false,false,true,true],"bearings":[30,75,150,240],"location":[-48.393892,-22.390034]},{"out":2,"in":0,"entry":[false,false,true],"bearings":[75,90,255],"location":[-48.394888,-22.390392]},{"out":1,"in":0,"entry":[false,true,true],"bearings":[75,255,345],"location":[-48.396369,-22.390694]},{"out":2,"in":0,"entry":[false,true,true],"bearings":[75,165,255],"location":[-48.398746,-22.391172]},{"out":3,"in":1,"entry":[true,false,true,true],"bearings":[30,75,195,255],"location":[-48.399711,-22.391379]},{"out":2,"in":1,"entry":[true,false,true],"bearings":[75,105,285],"location":[-48.407478,-22.391656]},{"out":2,"in":0,"entry":[false,true,true],"bearings":[105,225,285],"location":[-48.409666,-22.391275]},{"out":1,"in":0,"entry":[false,true,true],"bearings":[75,255,270],"location":[-48.420412,-22.39099]},{"out":2,"in":0,"entry":[false,true,true],"bearings":[75,165,255],"location":[-48.421107,-22.391168]},{"out":2,"in":1,"entry":[false,false,true],"bearings":[30,75,255],"location":[-48.421361,-22.39124]},{"out":2,"in":0,"entry":[false,true,true],"bearings":[75,240,255],"location":[-48.432293,-22.39447]},{"out":2,"in":1,"entry":[true,false,true],"bearings":[45,75,255],"location":[-48.432628,-22.394562]},{"out":1,"in":0,"entry":[false,true,true],"bearings":[75,255,330],"location":[-48.435135,-22.395301]},{"out":3,"in":1,"entry":[true,false,true,true],"bearings":[0,75,180,255],"location":[-48.447543,-22.398965]},{"out":2,"in":0,"entry":[false,true,true,true],"bearings":[75,135,255,300],"location":[-48.456611,-22.401645]},{"out":1,"in":0,"entry":[false,true,true],"bearings":[75,255,270],"location":[-48.458298,-22.402165]},{"out":2,"in":0,"entry":[false,false,true],"bearings":[75,240,255],"location":[-48.458723,-22.402301]},{"out":2,"in":0,"entry":[false,false,true,false],"bearings":[75,165,255,330],"location":[-48.459142,-22.402407]},{"out":3,"in":1,"entry":[false,false,false,true],"bearings":[0,75,165,255],"location":[-48.459556,-22.402538]},{"out":2,"in":0,"entry":[false,false,true],"bearings":[72,76,255],"location":[-48.460363,-22.402787]},{"out":2,"in":1,"entry":[false,false,true],"bearings":[60,75,255],"location":[-48.460619,-22.40285]},{"out":2,"in":0,"entry":[false,true,true],"bearings":[75,135,255],"location":[-48.46127,-22.403063]},{"out":1,"in":0,"entry":[false,true,true],"bearings":[75,255,330],"location":[-48.461334,-22.403082]},{"out":2,"in":0,"entry":[false,true,true],"bearings":[75,165,255],"location":[-48.469876,-22.405535]},{"out":2,"in":1,"entry":[true,false,true],"bearings":[0,90,270],"location":[-48.471768,-22.40582]},{"out":2,"in":1,"entry":[true,false,true],"bearings":[0,90,270],"location":[-48.472306,-22.405839]},{"out":2,"in":0,"entry":[false,false,true,true],"bearings":[94,263,274,290],"location":[-48.477018,-22.405569]},{"out":3,"in":1,"entry":[false,false,false,true],"bearings":[0,90,195,270],"location":[-48.477686,-22.405526]},{"out":3,"in":1,"entry":[false,false,false,true],"bearings":[15,90,165,270],"location":[-48.47857,-22.405486]},{"out":3,"in":1,"entry":[false,false,false,true],"bearings":[75,90,105,270],"location":[-48.479367,-22.405457]},{"out":3,"in":1,"entry":[true,false,false,true],"bearings":[45,150,255,330],"location":[-48.50088,-22.39035]},{"out":3,"in":1,"entry":[false,false,false,true],"bearings":[75,150,225,330],"location":[-48.501091,-22.390024]},{"out":2,"in":1,"entry":[true,false,true],"bearings":[60,150,330],"location":[-48.504542,-22.384534]},{"out":2,"in":1,"entry":[true,false,true],"bearings":[60,150,330],"location":[-48.5146,-22.369019]},{"out":2,"in":1,"entry":[true,false,true],"bearings":[45,150,330],"location":[-48.515271,-22.367974]},{"out":2,"in":0,"entry":[false,true,true],"bearings":[135,225,315],"location":[-48.519976,-22.362937]},{"out":2,"in":1,"entry":[true,false,true],"bearings":[30,135,315],"location":[-48.524802,-22.358993]},{"out":2,"in":1,"entry":[true,false,true],"bearings":[90,135,315],"location":[-48.526697,-22.357444]},{"out":3,"in":1,"entry":[true,false,false,true],"bearings":[30,135,240,315],"location":[-48.528626,-22.355883]},{"out":3,"in":1,"entry":[false,false,true,true],"bearings":[45,135,195,315],"location":[-48.52894,-22.355635]},{"out":2,"in":0,"entry":[false,true,true],"bearings":[135,210,315],"location":[-48.54045,-22.346241]},{"out":3,"in":1,"entry":[true,false,true,true],"bearings":[45,135,240,315],"location":[-48.543245,-22.343957]},{"out":2,"in":0,"entry":[false,false,true],"bearings":[135,300,315],"location":[-48.544624,-22.342842]},{"out":2,"in":0,"entry":[false,false,true],"bearings":[150,225,315],"location":[-48.545172,-22.34221]},{"out":1,"in":0,"entry":[false,true,true],"bearings":[135,315,345],"location":[-48.545452,-22.341954]},{"out":2,"in":1,"entry":[false,false,true],"bearings":[90,135,315],"location":[-48.54576,-22.341703]},{"out":2,"in":0,"entry":[false,true,true],"bearings":[135,255,300],"location":[-48.546076,-22.34147]},{"out":2,"in":0,"entry":[false,false,true],"bearings":[120,135,315],"location":[-48.546814,-22.341056]},{"out":2,"in":0,"entry":[false,true,true],"bearings":[135,180,315],"location":[-48.552502,-22.336416]},{"out":2,"in":0,"entry":[false,false,true],"bearings":[135,300,315],"location":[-48.55253,-22.336393]},{"out":2,"in":0,"entry":[false,false,true],"bearings":[135,180,315],"location":[-48.553145,-22.335695]},{"out":1,"in":0,"entry":[false,true,true],"bearings":[135,315,330],"location":[-48.553303,-22.335557]},{"out":2,"in":1,"entry":[false,false,true],"bearings":[90,135,315],"location":[-48.553879,-22.335085]},{"out":2,"in":0,"entry":[false,true,true],"bearings":[135,255,300],"location":[-48.554048,-22.33496]},{"out":2,"in":0,"entry":[false,false,true],"bearings":[120,135,315],"location":[-48.55485,-22.334492]},{"out":2,"in":0,"entry":[false,true,true],"bearings":[135,225,315],"location":[-48.554966,-22.334401]},{"out":2,"in":0,"entry":[false,true,true],"bearings":[135,195,315],"location":[-48.55672,-22.332972]},{"out":2,"in":0,"entry":[false,true,true],"bearings":[135,210,315],"location":[-48.558156,-22.331798]},{"out":2,"in":0,"entry":[false,false,true],"bearings":[135,300,315],"location":[-48.570125,-22.322062]}],"weight":1079.999999999,"duration":1079.999999999,"distance":22678.5},{"geometry":"jrfgC~pmgHc@`@YXURQNQJSHUDYD]By@D]HSHMJILILINGPITM\\MVMVIHKLQJUJk@HgCZuBZ","maneuver":{"bearing_after":317,"bearing_before":310,"location":[-48.571202,-22.321177],"modifier":"slight right","type":"on ramp"},"mode":"driving","driving_side":"right","name":"","intersections":[{"out":2,"in":0,"entry":[false,true,true],"bearings":[135,300,315],"location":[-48.571202,-22.321177]}],"weight":41.6,"duration":41.6,"distance":522.8},{"geometry":"tyegC~~mgHaJr@q@FaDReEZqC^cCPcG`@sJx@{Ir@yBNaA@","maneuver":{"bearing_after":351,"bearing_before":345,"location":[-48.573444,-22.317231],"modifier":"slight left","type":"merge"},"mode":"driving","ref":"SP-255; SP-304","driving_side":"right","name":"Contorno Rodoviário Antônio Prado Galvão de Barros","intersections":[{"out":2,"in":0,"entry":[false,false,true],"bearings":[165,180,345],"location":[-48.573444,-22.317231]},{"out":2,"in":1,"entry":[true,false,true],"bearings":[0,165,345],"location":[-48.573982,-22.313407]},{"out":0,"in":1,"entry":[true,false,false],"bearings":[0,165,180],"location":[-48.575033,-22.306513]}],"weight":49.5,"duration":49.5,"distance":1235.6},{"geometry":"rtcgC~hngHgENqBBe@@kDXa@@a@C[E","maneuver":{"bearing_after":355,"bearing_before":357,"location":[-48.575043,-22.306176],"modifier":"slight right","type":"off ramp"},"mode":"driving","driving_side":"right","name":"","intersections":[{"out":0,"in":1,"entry":[true,false,true],"bearings":[0,180,345],"location":[-48.575043,-22.306176]}],"weight":27.5,"duration":27.5,"distance":344.7},{"geometry":"facgCfjngH[S[I[C]BYDa@NKJMNM\\CTAT@XBTHPP\\TN","maneuver":{"exit":3,"bearing_after":33,"bearing_before":7,"location":[-48.575242,-22.303077],"modifier":"slight right","type":"roundabout"},"mode":"driving","ref":"SP-225; BR-369","driving_side":"right","name":"Rodovia Comandante João Ribeiro de Barros","intersections":[{"out":0,"in":1,"entry":[true,false,false],"bearings":[30,195,225],"location":[-48.575242,-22.303077]},{"out":0,"in":2,"entry":[true,true,false],"bearings":[15,45,210],"location":[-48.575143,-22.302942]},{"out":2,"in":1,"entry":[false,false,true],"bearings":[120,150,315],"location":[-48.575198,-22.30221]},{"out":1,"in":0,"entry":[false,true,true],"bearings":[135,300,330],"location":[-48.575338,-22.302081]},{"out":2,"in":1,"entry":[false,false,true],"bearings":[15,60,225],"location":[-48.576187,-22.302154]}],"weight":9.399999999,"duration":9.399999999,"distance":231.5},{"geometry":"b|bgCtpngH`@l@Zx@F\\B`@Bf@\\tMp@b[JxB`@jHxAto@N`JRhHXnF^xOLrFL~EFbCHjElB|x@t@r\\L~FBvAx@d]\\rNbEnjBZpMZvNFfBZrNd@bTX~Ld@|RJrEJvEJtEZdN\\lN\\|Oj@|U^zO@^TpKTlHJfGF|IHhFFxBZzMl@|W`@pKPlFLxDFzBf@|Ux@x\\\\jHh@pGjApIhAbHR`Aj@bC|AlGr@zBnC~Hf@xAnAtCnAhCnAfC`@r@rA~BlCdEzBbDtB`DxB|CvAjBHLHLzEfHhD~EpI~LlFnIpBfD`A~AtAjCtCtGxCjHjBdFjApDrAtEl@dCvAvGxAfIv@dJFp@z@hJ\\nDd@xEz@xIZlDjAfMt@tHn@zGT~B`@xEZ|CJ~@TdCxFtl@tBzRp@dHp@pHHx@lAbMpCzZnClYtAlNj@fGN`CVbDf@tFbAjKtBbU^tDLvA\\nFd@rFd@`Fp@bHH~@n@fIJ`AjCpXdCdXdE`c@dAbLLvAt@|Hr@zHlAtMp@nLF`AV~ERzEZhIX~MFbJ?hMOzP_@zR_ApSu@fMcA|Ls@jHWfCiAvK}CdZ_DjZ{CxYMtAgC`VoCzWmAvL[bDi@fFwCxXsBxRi@`FcCbVmAnLmAdLcCxUgCnVcCnUgBbQCVa@|DqB`RwBtSkApKuA`Nc@tFKz@q@bHKdAs@xGgAbJOxAq@`HiDl[_@dDwBvRyDb_@oObyAcEz`@yA|M?\\aEtb@Gn@g@rEmChVcFvf@o@~Gg@nEg@tE{@`Je@|EUtB","maneuver":{"exit":3,"bearing_after":230,"bearing_before":216,"location":[-48.576272,-22.302256],"modifier":"straight","type":"exit roundabout"},"mode":"driving","ref":"SP-225; BR-369","driving_side":"right","name":"Rodovia Comandante João Ribeiro de Barros","intersections":[{"out":2,"in":0,"entry":[false,true,true],"bearings":[45,210,225],"location":[-48.576272,-22.302256]},{"out":1,"in":0,"entry":[false,true,true],"bearings":[84,263,271],"location":[-48.584769,-22.303108]},{"out":2,"in":1,"entry":[false,false,true],"bearings":[75,90,270],"location":[-48.597318,-22.30391]},{"out":1,"in":0,"entry":[false,true,true],"bearings":[86,267,271],"location":[-48.60121,-22.304197]},{"out":2,"in":1,"entry":[false,false,true],"bearings":[75,90,270],"location":[-48.604207,-22.304376]},{"out":1,"in":0,"entry":[false,true,true],"bearings":[86,267,271],"location":[-48.614503,-22.304981]},{"out":2,"in":0,"entry":[false,false,true],"bearings":[84,87,266],"location":[-48.620957,-22.305342]},{"out":1,"in":0,"entry":[false,true,true],"bearings":[90,270,285],"location":[-48.625788,-22.305633]},{"out":2,"in":1,"entry":[false,false,true],"bearings":[75,90,270],"location":[-48.628291,-22.305777]},{"out":1,"in":0,"entry":[false,true,true],"bearings":[86,267,276],"location":[-48.647824,-22.3069]},{"out":2,"in":1,"entry":[false,false,true],"bearings":[75,90,270],"location":[-48.650339,-22.307039]},{"out":1,"in":0,"entry":[false,true,true],"bearings":[90,270,345],"location":[-48.67936,-22.308729]},{"out":1,"in":0,"entry":[false,true,true],"bearings":[90,270,285],"location":[-48.687886,-22.30915]},{"out":2,"in":1,"entry":[false,false,true],"bearings":[75,90,270],"location":[-48.696267,-22.309691]},{"out":1,"in":0,"entry":[false,true,true],"bearings":[75,255,285],"location":[-48.714463,-22.311808]},{"out":2,"in":1,"entry":[false,false,true],"bearings":[45,60,240],"location":[-48.716429,-22.312538]},{"out":1,"in":0,"entry":[false,true,true],"bearings":[60,240,255],"location":[-48.738169,-22.326541]},{"out":2,"in":1,"entry":[false,false,true],"bearings":[54,67,250],"location":[-48.740134,-22.327339]},{"out":1,"in":0,"entry":[false,true,true],"bearings":[75,255,345],"location":[-48.74857,-22.329234]},{"out":1,"in":0,"entry":[false,true,true],"bearings":[75,255,345],"location":[-48.754536,-22.330235]},{"out":2,"in":1,"entry":[false,false,true],"bearings":[60,75,255],"location":[-48.759241,-22.331032]},{"out":1,"in":0,"entry":[false,true,true],"bearings":[75,255,270],"location":[-48.761022,-22.331338]},{"out":1,"in":0,"entry":[false,true,true],"bearings":[75,255,270],"location":[-48.77151,-22.33318]},{"out":2,"in":1,"entry":[false,false,true],"bearings":[45,75,255],"location":[-48.772984,-22.333426]},{"out":1,"in":0,"entry":[false,true,true],"bearings":[75,255,270],"location":[-48.792237,-22.336617]},{"out":2,"in":1,"entry":[false,false,true],"bearings":[69,80,260],"location":[-48.798667,-22.337709]},{"out":1,"in":0,"entry":[false,true,true],"bearings":[75,255,270],"location":[-48.801534,-22.338124]},{"out":2,"in":1,"entry":[false,false,true],"bearings":[60,75,255],"location":[-48.806081,-22.338849]},{"out":1,"in":0,"entry":[false,true,true],"bearings":[80,263,273],"location":[-48.828361,-22.342607]},{"out":2,"in":1,"entry":[false,false,true],"bearings":[75,90,270],"location":[-48.833073,-22.343118]},{"out":1,"in":0,"entry":[false,true,true],"bearings":[105,285,300],"location":[-48.856528,-22.341997]},{"out":2,"in":1,"entry":[false,false,true],"bearings":[90,105,285],"location":[-48.857213,-22.341875]},{"out":1,"in":0,"entry":[false,true,true],"bearings":[105,285,345],"location":[-48.872697,-22.339069]},{"out":1,"in":0,"entry":[false,true,true],"bearings":[105,285,300],"location":[-48.882568,-22.337281]},{"out":2,"in":1,"entry":[false,false,true],"bearings":[75,105,285],"location":[-48.883389,-22.337136]},{"out":1,"in":0,"entry":[false,true,true],"bearings":[105,285,345],"location":[-48.891847,-22.335592]},{"out":1,"in":0,"entry":[false,true,true],"bearings":[101,281,285],"location":[-48.896675,-22.334718]},{"out":2,"in":1,"entry":[false,false,true],"bearings":[90,105,285],"location":[-48.904601,-22.333279]},{"out":2,"in":1,"entry":[true,false,true],"bearings":[15,105,285],"location":[-48.928239,-22.329011]},{"out":2,"in":1,"entry":[true,false,true],"bearings":[15,105,285],"location":[-48.933691,-22.328004]},{"out":2,"in":1,"entry":[true,false,true],"bearings":[15,105,285],"location":[-48.94052,-22.326744]},{"out":1,"in":0,"entry":[false,true,true],"bearings":[102,281,289],"location":[-48.943683,-22.326136]},{"out":2,"in":1,"entry":[false,false,true],"bearings":[90,105,285],"location":[-48.948824,-22.325209]},{"out":1,"in":0,"entry":[false,true,true],"bearings":[101,278,284],"location":[-48.971049,-22.321142]},{"out":2,"in":1,"entry":[false,false,true],"bearings":[90,105,285],"location":[-48.988297,-22.318078]},{"out":1,"in":0,"entry":[false,true,true],"bearings":[101,281,285],"location":[-48.990776,-22.317642]},{"out":2,"in":1,"entry":[false,false,true],"bearings":[90,105,285],"location":[-48.994725,-22.316946]}],"weight":1832.2,"duration":1832.2,"distance":44203.1},{"geometry":"fwegCvk`jHg@dF[tCOdBKxC@j@Bl@HdA\\jBh@jBd@hAh@hA`ArAbC~BpB`BvBfBvE~DxItHlEtD`DlClB~AfBzAvD~CfCzBx@p@|F`FxE|DnGlF|EdErFxEjFnEnErD|GnFhAhA~M~KlKvInAfAvHrGxFhFdH`GrCfClMjKxMdLTH`NlLtIrHbEnD","maneuver":{"bearing_after":279,"bearing_before":279,"location":[-48.995317,-22.31684],"modifier":"straight","type":"new name"},"mode":"driving","ref":"SP-225; BR-369","driving_side":"right","name":"Rodovia Engenheiro João Baptista Cabral Rennó","intersections":[{"out":1,"in":0,"entry":[false,true,true],"bearings":[101,281,287],"location":[-48.995317,-22.31684]},{"out":2,"in":1,"entry":[false,false,true],"bearings":[90,95,269],"location":[-48.9985,-22.316361]},{"out":1,"in":0,"entry":[false,true,true],"bearings":[81,253,257],"location":[-48.999297,-22.316441]},{"out":1,"in":0,"entry":[false,true,true],"bearings":[40,220,224],"location":[-49.004151,-22.320439]},{"out":2,"in":0,"entry":[false,false,true],"bearings":[30,45,225],"location":[-49.009064,-22.326002]},{"out":1,"in":0,"entry":[false,true,true],"bearings":[45,225,255],"location":[-49.018424,-22.336667]},{"out":2,"in":1,"entry":[false,false,true],"bearings":[15,45,225],"location":[-49.018785,-22.337039]},{"out":1,"in":0,"entry":[false,true,true],"bearings":[39,219,230],"location":[-49.020869,-22.339441]},{"out":2,"in":1,"entry":[false,false,true],"bearings":[30,45,225],"location":[-49.024334,-22.343386]},{"out":1,"in":0,"entry":[false,true,true],"bearings":[45,210,225],"location":[-49.031556,-22.351533]},{"out":2,"in":1,"entry":[false,false,true],"bearings":[30,45,225],"location":[-49.035295,-22.355757]}],"weight":257.5,"duration":257.5,"distance":6300.1},{"geometry":"rpmgCbkhjHnAbCxBlBJJnCzBlDhC`@^~@bA`@d@R`@L^D^Bj@Af@Mn@Oh@c@p@g@^w@Zg@Hs@LcDr@]HaAR[BY@u@O[GYGWE_@Ai@DcAP_@FIBUJ[Ne@f@s@`A","maneuver":{"bearing_after":236,"bearing_before":219,"location":[-49.036183,-22.356744],"modifier":"slight right","type":"fork"},"mode":"driving","driving_side":"right","name":"Rua Levy Lenotti","intersections":[{"out":2,"in":0,"entry":[false,true,true],"bearings":[45,225,240],"location":[-49.036183,-22.356744]},{"out":1,"in":0,"entry":[false,true,true],"bearings":[60,225,315],"location":[-49.036844,-22.35714]},{"out":1,"in":0,"entry":[false,true,true],"bearings":[45,225,315],"location":[-49.037447,-22.357806]},{"out":1,"in":0,"entry":[false,true,true],"bearings":[45,210,330],"location":[-49.038073,-22.358533]},{"out":1,"in":0,"entry":[false,true,true],"bearings":[30,225,255],"location":[-49.038764,-22.359395]},{"out":2,"in":0,"entry":[false,true,true],"bearings":[45,135,225],"location":[-49.03892,-22.35957]},{"out":2,"in":0,"entry":[false,false,true],"bearings":[150,165,345],"location":[-49.041361,-22.359457]},{"out":2,"in":1,"entry":[true,false,true],"bearings":[75,165,345],"location":[-49.041484,-22.359004]},{"out":2,"in":1,"entry":[true,false,true],"bearings":[45,165,345],"location":[-49.041743,-22.358176]},{"out":3,"in":1,"entry":[true,false,false,true],"bearings":[75,165,255,345],"location":[-49.041839,-22.356059]},{"out":3,"in":1,"entry":[false,false,true,true],"bearings":[90,165,255,330],"location":[-49.041884,-22.355895]}],"weight":53.4,"duration":53.4,"distance":1261.3},{"geometry":"tfmgC`sijH_B~@}Ad@u@P{Cr@eCh@yDr@gGlA{HbBa@H_LtB","maneuver":{"bearing_after":327,"bearing_before":309,"location":[-49.042571,-22.355153],"modifier":"straight","type":"new name"},"mode":"driving","driving_side":"right","name":"Rua Sérgio Arcangelo","intersections":[{"out":2,"in":0,"entry":[false,true,true],"bearings":[135,315,330],"location":[-49.042571,-22.355153]},{"out":2,"in":1,"entry":[true,false,true],"bearings":[75,165,345],"location":[-49.043078,-22.354196]},{"out":2,"in":1,"entry":[true,false,true],"bearings":[75,165,345],"location":[-49.043429,-22.353145]},{"out":2,"in":1,"entry":[true,false,true],"bearings":[75,165,345],"location":[-49.043903,-22.351553]},{"out":2,"in":1,"entry":[true,false,true],"bearings":[75,165,345],"location":[-49.044288,-22.350229]},{"out":2,"in":0,"entry":[false,false,true],"bearings":[165,180,345],"location":[-49.044844,-22.348475]}],"weight":43,"duration":43,"distance":1015.2},{"geometry":"~okgC|djjHgBb@kStDyGxAe@JcCd@{@NoARaB\\q@JoG|AiQrDmE|@gGhAwDr@","maneuver":{"bearing_after":341,"bearing_before":344,"location":[-49.045433,-22.346403],"modifier":"straight","type":"turn"},"mode":"driving","driving_side":"right","name":"Rodovia Marechal Rondon (Marginal)","intersections":[{"out":1,"in":0,"entry":[false,true,true],"bearings":[165,342,350],"location":[-49.045433,-22.346403]},{"out":2,"in":1,"entry":[true,false,true],"bearings":[15,165,345],"location":[-49.046974,-22.341212]},{"out":2,"in":1,"entry":[false,false,true],"bearings":[135,165,345],"location":[-49.047301,-22.340062]},{"out":2,"in":1,"entry":[true,false,true],"bearings":[15,165,345],"location":[-49.047614,-22.338917]},{"out":2,"in":1,"entry":[false,false,true],"bearings":[135,165,345],"location":[-49.048075,-22.337562]},{"out":2,"in":1,"entry":[true,false,true],"bearings":[75,165,345],"location":[-49.048977,-22.334633]},{"out":2,"in":0,"entry":[false,true,true],"bearings":[165,330,345],"location":[-49.049293,-22.3336]},{"out":2,"in":1,"entry":[true,false,true],"bearings":[75,165,345],"location":[-49.04966,-22.332283]}],"weight":73.3,"duration":73.3,"distance":1729.4},{"geometry":"~qhgC~`kjHmDt@kDt@","maneuver":{"bearing_after":343,"bearing_before":344,"location":[-49.049919,-22.331357],"modifier":"straight","type":"new name"},"mode":"driving","driving_side":"right","name":"Rua Amazonas","intersections":[{"out":2,"in":1,"entry":[true,false,true],"bearings":[75,165,345],"location":[-49.049919,-22.331357]},{"out":2,"in":1,"entry":[true,false,true],"bearings":[75,165,345],"location":[-49.05019,-22.330486]}],"weight":8.5,"duration":8.5,"distance":199.1},{"geometry":"dghgCjdkjHqDp@iDp@aAXq@NgF~@_Dh@","maneuver":{"bearing_after":344,"bearing_before":343,"location":[-49.050455,-22.32963],"modifier":"straight","type":"new name"},"mode":"driving","driving_side":"right","name":"Rodovia Marechal Rondon (Marginal)","intersections":[{"out":2,"in":1,"entry":[true,false,true],"bearings":[75,165,345],"location":[-49.050455,-22.32963]},{"out":2,"in":1,"entry":[true,false,true],"bearings":[75,165,345],"location":[-49.050705,-22.328743]},{"out":2,"in":1,"entry":[true,false,true],"bearings":[75,165,345],"location":[-49.05096,-22.327887]},{"out":2,"in":1,"entry":[true,false,true],"bearings":[0,165,345],"location":[-49.051085,-22.327563]}],"weight":20.799999999,"duration":20.799999999,"distance":491.5},{"geometry":"llggCblkjHMB@T@`B?T\\zDf@|D\\~D\\|Dd@~DB\\H`@`@|Cp@xDl@zDVlB","maneuver":{"bearing_after":341,"bearing_before":345,"location":[-49.051699,-22.325347],"modifier":"left","type":"turn"},"mode":"driving","driving_side":"right","name":"Avenida Duque de Caxias","intersections":[{"out":3,"in":1,"entry":[true,false,false,true],"bearings":[90,165,270,345],"location":[-49.051699,-22.325347]},{"out":2,"in":1,"entry":[false,false,true,true],"bearings":[90,165,270,345],"location":[-49.051721,-22.32528]},{"out":2,"in":0,"entry":[false,true,true,false],"bearings":[90,165,255,345],"location":[-49.052427,-22.325303]},{"out":2,"in":0,"entry":[false,false,true,true],"bearings":[75,165,255,345],"location":[-49.053372,-22.325445]},{"out":2,"in":0,"entry":[false,true,true,false],"bearings":[75,165,255,345],"location":[-49.054322,-22.325645]},{"out":2,"in":0,"entry":[false,false,true,true],"bearings":[75,165,255,345],"location":[-49.055281,-22.325798]},{"out":2,"in":0,"entry":[false,true,true,false],"bearings":[75,180,255,345],"location":[-49.056227,-22.325953]},{"out":2,"in":0,"entry":[false,true,true,true],"bearings":[75,150,255,345],"location":[-49.057194,-22.326135]},{"out":2,"in":0,"entry":[false,true,true],"bearings":[75,180,255],"location":[-49.057337,-22.326163]},{"out":1,"in":0,"entry":[false,true,true],"bearings":[75,255,345],"location":[-49.05751,-22.326206]},{"out":2,"in":0,"entry":[false,true,true,false],"bearings":[75,165,255,345],"location":[-49.058295,-22.326383]},{"out":2,"in":0,"entry":[false,false,true,true],"bearings":[75,165,255,345],"location":[-49.059228,-22.326625]},{"out":2,"in":0,"entry":[false,true,true,false],"bearings":[75,165,255,345],"location":[-49.060165,-22.326855]}],"weight":65.6,"duration":65.6,"distance":955.4},{"geometry":"rvggCndmjHFrADx@Ad@Eb@K`@O^QZMLKR","maneuver":{"bearing_after":264,"bearing_before":255,"location":[-49.060718,-22.326981],"modifier":"slight right","type":"continue"},"mode":"driving","driving_side":"right","name":"Avenida Duque de Caxias","intersections":[{"out":2,"in":0,"entry":[false,true,true],"bearings":[75,255,270],"location":[-49.060718,-22.326981]},{"out":2,"in":0,"entry":[false,true,true,false],"bearings":[90,165,270,345],"location":[-49.061138,-22.327019]}],"weight":27.3,"duration":27.3,"distance":189.5},{"geometry":"ptggCfomjH_@TuBpBg@`@a@\\gA`AuCtCu@p@cBxA{ChC_@ZkDxC","maneuver":{"bearing_after":324,"bearing_before":302,"location":[-49.062435,-22.326653],"modifier":"slight right","type":"turn"},"mode":"driving","driving_side":"right","name":"Avenida Nações Unidas","intersections":[{"out":2,"in":0,"entry":[false,false,true],"bearings":[120,150,330],"location":[-49.062435,-22.326653]},{"lanes":[{"valid":true,"indications":["straight","left"]},{"valid":true,"indications":["none"]},{"valid":true,"indications":["none"]}],"out":2,"in":1,"entry":[true,false,true],"bearings":[75,150,315],"location":[-49.062552,-22.326494]},{"lanes":[{"valid":true,"indications":["straight","left"]},{"valid":true,"indications":["none"]},{"valid":true,"indications":["none"]}],"out":2,"in":0,"entry":[false,true,true],"bearings":[135,300,315],"location":[-49.063116,-22.325897]},{"out":2,"in":1,"entry":[false,false,true],"bearings":[75,135,315],"location":[-49.063293,-22.325697]},{"out":2,"in":0,"entry":[false,false,true],"bearings":[135,210,315],"location":[-49.063441,-22.325534]},{"out":2,"in":1,"entry":[true,false,true],"bearings":[75,135,315],"location":[-49.063766,-22.325172]},{"out":2,"in":1,"entry":[false,false,true],"bearings":[75,135,315],"location":[-49.064524,-22.324424]},{"lanes":[{"valid":true,"indications":["straight","left"]},{"valid":true,"indications":["none"]},{"valid":true,"indications":["none"]}],"out":1,"in":0,"entry":[false,true,true],"bearings":[135,315,345],"location":[-49.064774,-22.324153]},{"lanes":[{"valid":true,"indications":["straight","left"]},{"valid":true,"indications":["none"]},{"valid":true,"indications":["none"]}],"out":3,"in":1,"entry":[true,false,true,true],"bearings":[75,135,255,315],"location":[-49.065221,-22.32365]},{"out":3,"in":1,"entry":[false,false,true,true],"bearings":[75,135,255,315],"location":[-49.065907,-22.322874]},{"out":1,"in":0,"entry":[false,true,true],"bearings":[135,315,345],"location":[-49.066052,-22.322707]}],"weight":56.399999999,"duration":56.399999999,"distance":698.2},{"geometry":"pvfgCrjnjHQLDZn@tDn@fE","maneuver":{"bearing_after":323,"bearing_before":319,"location":[-49.066817,-22.321847],"modifier":"left","type":"turn"},"mode":"driving","driving_side":"right","name":"Avenida Rodrigues Alves","intersections":[{"out":3,"in":1,"entry":[true,false,false,true],"bearings":[75,135,255,330],"location":[-49.066817,-22.321847]},{"out":2,"in":1,"entry":[false,false,true,true],"bearings":[75,150,255,315],"location":[-49.066886,-22.321759]},{"out":2,"in":0,"entry":[false,true,true,false],"bearings":[75,135,255,315],"location":[-49.067033,-22.321793]},{"out":2,"in":0,"entry":[false,true,true,false],"bearings":[75,165,255,345],"location":[-49.067937,-22.322027]}],"weight":29.8,"duration":29.8,"distance":230.6},{"geometry":"dyfgCzwnjHcBXqDr@","maneuver":{"bearing_after":345,"bearing_before":254,"location":[-49.068936,-22.322265],"modifier":"right","type":"turn"},"mode":"driving","driving_side":"right","name":"Rua Araújo Leite","intersections":[{"out":3,"in":0,"entry":[false,false,true,true],"bearings":[75,165,255,345],"location":[-49.068936,-22.322265]},{"out":3,"in":1,"entry":[true,false,false,true],"bearings":[75,165,255,345],"location":[-49.069069,-22.321771]}],"weight":28.2,"duration":28.2,"distance":159.1},{"geometry":"npfgChznjHl@bE","maneuver":{"bearing_after":254,"bearing_before":344,"location":[-49.069329,-22.320876],"modifier":"left","type":"turn"},"mode":"driving","driving_side":"right","name":"Rua Primeiro de Agosto","intersections":[{"out":2,"in":1,"entry":[false,false,true,true],"bearings":[75,165,255,345],"location":[-49.069329,-22.320876]}],"weight":20.4,"duration":20.4,"distance":104.5},{"geometry":"|qfgCl`ojHvB_@","maneuver":{"bearing_after":165,"bearing_before":254,"location":[-49.070312,-22.32111],"modifier":"left","type":"turn"},"mode":"driving","driving_side":"right","name":"Rua Antônio Alves","intersections":[{"out":1,"in":0,"entry":[false,true,true,false],"bearings":[75,165,255,345],"location":[-49.070312,-22.32111]}],"weight":9.8,"duration":9.8,"distance":68.6},{"geometry":"tufgCl_ojH","maneuver":{"bearing_after":0,"bearing_before":166,"location":[-49.070153,-22.321712],"modifier":"right","type":"arrive"},"mode":"driving","driving_side":"right","name":"Rua Antônio Alves","intersections":[{"in":0,"entry":[true],"bearings":[346],"location":[-49.070153,-22.321712]}],"weight":0,"duration":0,"distance":0}],"summary":"Rodovia Deputado Amauri Barroso de Souza, Rodovia Comandante João Ribeiro de Barros","weight":3976.1,"duration":3976.1,"distance":85551.4}],"weight_name":"routability","weight":3976.1,"duration":3976.1,"distance":85551.4}],"waypoints":[{"hint":"IYfwhCSH8IQ6AAAANAAAACsAAAAAAAAAUaAhQrWTEEJ4KvBBAAAAADoAAAA0AAAAKwAAAAAAAACyhAAAxbYd_amqqv7stR39Jaqq_gEAbxQgbuoe","distance":26.704193292,"name":"Avenida José Alves Mira","location":[-48.384315,-22.369623]},{"hint":"j0KphP___39iAAAAlAAAAAAAAAAAAAAAeEqJQsbPCEIAAAAAAAAAAGIAAACUAAAAAAAAAAAAAACyhAAAtz8T_dBlq_4GPhP9bmWr_gAAbwogbuoe","distance":45.91089501,"name":"Rua Antônio Alves","location":[-49.070153,-22.321712]}],"origem":"Dois Córregos, Região Imediata de Jaú, Região Geográfica Intermediária de Bauru, São Paulo, Região Sudeste, 17300-000, Brasil","destino":"Bauru-SP","paradas":[],"instrucoes":[{"summary":"Rodovia Deputado Amauri Barroso de Souza, Rodovia Comandante João Ribeiro de Barros","distance":"80,8 km","duration":"1 h 6 min","steps":[{"instruction":"Partir do ponto inicial","distance":"130 m","duration":"0 min 17 s"},{"instruction":"Virar à esquerda","distance":"596 m","duration":"1 min 6 s"},{"instruction":"Continuar em em frente","distance":"222 m","duration":"0 min 29 s"},{"instruction":"Fim da estrada à esquerda","distance":"10 m","duration":"0 min 1 s"},{"instruction":"Pegar o desvio levemente à direita","distance":"2,0 km","duration":"2 min 10 s"},{"instruction":"Virar em frente","distance":"22,7 km","duration":"17 min 60 s"},{"instruction":"Entrar na rampa levemente à direita","distance":"523 m","duration":"0 min 42 s"},{"instruction":"Juntar-se a levemente à esquerda","distance":"1,2 km","duration":"0 min 50 s"},{"instruction":"Sair pela rampa levemente à direita","distance":"345 m","duration":"0 min 28 s"},{"instruction":"Entrar na rotatória e sair levemente à direita","distance":"232 m","duration":"0 min 9 s"},{"instruction":"Sair da rotatória em frente","distance":"43,7 km","duration":"30 min 13 s"},{"instruction":"Sair pela rampa levemente à direita","distance":"730 m","duration":"0 min 58 s"},{"instruction":"Virar em frente","distance":"741 m","duration":"0 min 49 s"},{"instruction":"Entrar na rotatória e sair em frente","distance":"89 m","duration":"0 min 6 s"},{"instruction":"Sair da rotatória em frente","distance":"3,4 km","duration":"3 min 45 s"},{"instruction":"Entrar na rotatória e sair levemente à direita","distance":"35 m","duration":"0 min 2 s"},{"instruction":"Sair da rotatória em frente","distance":"3,7 km","duration":"5 min 2 s"},{"instruction":"Virar à direita","distance":"159 m","duration":"0 min 28 s"},{"instruction":"Virar à esquerda","distance":"105 m","duration":"0 min 20 s"},{"instruction":"Virar à esquerda","distance":"69 m","duration":"0 min 10 s"},{"instruction":"Chegar ao destino (à direita)","distance":"0 m","duration":"0 min"}]}]},"origem":"Dois Córregos-SP","paradas":["Bauru-SP"],"instrucoes":[{"summary":"Rodovia Deputado Amauri Barroso de Souza, Rodovia Comandante João Ribeiro de Barros","distance":"80,8 km","duration":"1 h 6 min","steps":[{"instruction":"Partir do ponto inicial","distance":"130 m","duration":"0 min 17 s"},{"instruction":"Virar à esquerda","distance":"596 m","duration":"1 min 6 s"},{"instruction":"Continuar em em frente","distance":"222 m","duration":"0 min 29 s"},{"instruction":"Fim da estrada à esquerda","distance":"10 m","duration":"0 min 1 s"},{"instruction":"Pegar o desvio levemente à direita","distance":"2,0 km","duration":"2 min 10 s"},{"instruction":"Virar em frente","distance":"22,7 km","duration":"17 min 60 s"},{"instruction":"Entrar na rampa levemente à direita","distance":"523 m","duration":"0 min 42 s"},{"instruction":"Juntar-se a levemente à esquerda","distance":"1,2 km","duration":"0 min 50 s"},{"instruction":"Sair pela rampa levemente à direita","distance":"345 m","duration":"0 min 28 s"},{"instruction":"Entrar na rotatória e sair levemente à direita","distance":"232 m","duration":"0 min 9 s"},{"instruction":"Sair da rotatória em frente","distance":"43,7 km","duration":"30 min 13 s"},{"instruction":"Sair pela rampa levemente à direita","distance":"730 m","duration":"0 min 58 s"},{"instruction":"Virar em frente","distance":"741 m","duration":"0 min 49 s"},{"instruction":"Entrar na rotatória e sair em frente","distance":"89 m","duration":"0 min 6 s"},{"instruction":"Sair da rotatória em frente","distance":"3,4 km","duration":"3 min 45 s"},{"instruction":"Entrar na rotatória e sair levemente à direita","distance":"35 m","duration":"0 min 2 s"},{"instruction":"Sair da rotatória em frente","distance":"3,7 km","duration":"5 min 2 s"},{"instruction":"Virar à direita","distance":"159 m","duration":"0 min 28 s"},{"instruction":"Virar à esquerda","distance":"105 m","duration":"0 min 20 s"},{"instruction":"Virar à esquerda","distance":"69 m","duration":"0 min 10 s"},{"instruction":"Chegar ao destino (à direita)","distance":"0 m","duration":"0 min"}]}],"optimized":false,"originalWaypointsOrder":[],"optimizedWaypointsOrder":[],"valorPedagios":"R$ 26,60","tipoVeiculo":"caminhao_2_eixos","pontosInteresse":[{"tipo":"tollbooth","nome":"Pedágio SP-225 - Jaú KM 199.300","posicao":[-22.2347,-48.7268],"detalhe":"Concessionária Cart - Rodovia Comandante João Ribeiro de Barros","naRota":true,"valor":"R$ 26,60"},{"tipo":"weighingstation","nome":"Balança DER SP-225","posicao":[-22.3368,-48.6933],"detalhe":"Horário: 6h às 18h (dias úteis) - Entre Jaú e Bauru","naRota":true}],"rotasAlternativas":[{"polyline":"bapgC~`ifHu@d@kCdB`BzCbB~CdBbD`B|C`B~Ch@bAZj@DH`@b@FDp@p@d@l@dBdBzA|ANKLGLAN?VBJFRHfBr@jAd@PFJDp@VTHh@R|@ZbEzANDvGzBfDnAJL^Nl@RhFbBv@V~@Rp@JRDL@vAVBHFFHDF@F@BAFADEVGXGREVAp@Ej@Cd@Ad@Gf@GjAO~B]hAO~@OjAQbAQlAQh@GZGXCx@MtB]bAOn@Ij@GpAKf@@XDXHXLZTPNNb@L`@Pl@Hb@Ln@z@fHrAbLJv@h@~DTbB^~Cd@bENzAHrADzABvA@xA?dAChAG`BE~@ShCc@nEu@pHUbCe@vEe@|E]|DOlBOzCMdDEjEBzCDxBHpBN~BP|BN`BL`ANhAPnAPz@Lp@^lB`@xB\\rBh@~BdChMtJbf@PbAVnAzAxH^jB~Ldn@|Gh]jD~PbArFd@xBr@lDXtAZbBvC~NfBpIXrATrAXrAp@~CJr@h@`CBJxDrSxGd]VrAB\\n@~GBz@DnAAZEpBo@zXGdCGnDE~CUlLQ~EO`C_@rCi@`C{@zC_AhC_ApB}A~CkRx_@wAnCuA~BoAjBkAzAaB~A}ApA{AfA_BbAiLnGyM|H{JpFaAh@{CfBgShKeH~DcRnK}HlEgTzL}MtHoFvCoIvEiH`EkCxAcB`AmBbAaCtA{@h@w@j@_An@w@n@eAz@cAz@}@v@_A~@iAjAgAlAo@r@}@pAwBpCoB`CqBhCiA|AkDtE}HbKuHzJwH`Ko@|@aBvBoCnD{AnB}@nAoA~AmA`BeC|CkA~A_CzCwBpC}ArBuAhB{ElG_DbE{DdFwBpCGJ_MbP_FpGUVWT]V[TUPUT]`@q@|@OROTMTKRM^Sb@OVS`@yFpH}FpHgLlOEDSPYVi@b@q@l@[\\e@l@e@l@QVY`@MXMTQ`@Sb@[h@QV}G|IiF~GcIjKoMxPiCdDkCjDyH~Jg@p@gDlEuAfBgB`CiDvE{@fAi@r@iAxAc@`@YXURQNQJSHUDYD]By@D]HSHMJILILINGPITM\\MVMVIHKLQJUJk@HgCZuBZaJr@q@FaDReEZqC^cCPcG`@sJx@{Ir@yBNaA@gENqBBe@@kDXa@@a@C[E[S[I[C]BYDa@NKJMNM\\CTAT@XBTHPP\\TN`@l@Zx@F\\B`@Bf@\\tMp@b[JxB`@jHxAto@N`JRhHXnF^xOLrFL~EFbCHjElB|x@t@r\\L~FBvAx@d]\\rNbEnjBZpMZvNFfBZrNd@bTX~Ld@|RJrEJvEJtEZdN\\lN\\|Oj@|U^zO@^TpKTlHJfGF|IHhFFxBZzMl@|W`@pKPlFLxDFzBf@|Ux@x\\\\jHh@pGjApIhAbHR`Aj@bC|AlGr@zBnC~Hf@xAnAtCnAhCnAfC`@r@rA~BlCdEzBbDtB`DxB|CvAjBHLHLzEfHhD~EpI~LlFnIpBfD`A~AtAjCtCtGxCjHjBdFjApDrAtEl@dCvAvGxAfIv@dJFp@z@hJ\\nDd@xEz@xIZlDjAfMt@tHn@zGT~B`@xEZ|CJ~@TdCxFtl@tBzRp@dHp@pHHx@lAbMpCzZnClYtAlNj@fGN`CVbDf@tFbAjKtBbU^tDLvA\\nFd@rFd@`Fp@bHH~@n@fIJ`AjCpXdCdXdE`c@dAbLLvAt@|Hr@zHlAtMp@nLF`AV~ERzEZhIX~MFbJ?hMOzP_@zR_ApSu@fMcA|Ls@jHWfCiAvK}CdZ_DjZ{CxYMtAgC`VoCzWmAvL[bDi@fFwCxXsBxRi@`FcCbVmAnLmAdLcCxUgCnVcCnUgBbQCVa@|DqB`RwBtSkApKuA`Nc@tFKz@q@bHKdAs@xGgAbJOxAq@`HiDl[_@dDwBvRyDb_@oObyAcEz`@yA|M?\\aEtb@Gn@g@rEmChVcFvf@o@~Gg@nEu@~EMt@Wr@s@hAgM~NoD`EmB|B[^iBtBqB~BqCdDuBbCmC~C{@r@c@X_@P[Lc@TMDE@YT]\\OTKRAPQn@Sl@[r@a@n@e@l@m@`Ae@`A]~@WdAQjAK~@E~@AnABjAFv@R`BX`B`@hCXhBVbB`@hCn@hEhEpXtA|I|A|Jh@fDxBfNB^@\\AzBGzBBd@Hb@ZdAl@tAh@hAPd@Jf@~@hGLx@nDjUJj@`AnGPp@LdADj@Bh@Bj@?R@r@EP?PBLFLVn@n@fBV~@v@dFz@dFT|ARnAr@vDfAvGz@bGDZVxAj@lDn@lEn@rEj@fDJd@r@lEXnBRzAt@pEp@nEd@rCLt@d@zCF\\^bChAhHd@`DLbAx@vE\\|BNbAVrAVhBz@zFh@hD~AtJ@Nj@hDh@fDf@fDf@hDVdBDZn@tDn@fEcBXqDr@l@bEvB_@","distancia":"80,8 km","tempo":"1 h 6 min","distanciaNumerica":80755.2,"tempoNumerico":3962.3,"destaque":true},{"polyline":"bapgC~`ifHu@d@kCdB`BzCbB~CdBbD`B|C`B~Ch@bAZj@DH`@b@FDp@p@d@l@dBdBzA|ANKLGLAN?VBJFRHfBr@jAd@PFJDp@VTHh@R|@ZbEzANDvGzBfDnAJL^Nl@RhFbBv@V~@Rp@JRDL@vAVBHFFHDF@F@BAFADEVGXGREVAp@Ej@Cd@Ad@Gf@GjAO~B]hAO~@OjAQbAQlAQh@GZGXCx@MtB]bAOn@Ij@GpAKf@@XDXHXLZTPNNb@L`@Pl@Hb@Ln@z@fHrAbLJv@h@~DTbB^~Cd@bENzAHrADzABvA@xA?dAChAG`BE~@ShCc@nEu@pHUbCe@vEe@|E]|DOlBOzCMdDEjEBzCDxBHpBN~BP|BN`BL`ANhAPnAPz@Lp@^lB`@xB\\rBh@~BdChMtJbf@PbAVnAzAxH^jB~Ldn@|Gh]jD~PbArFd@xBr@lDXtAZbBvC~NfBpIXrATrAXrAp@~CJr@h@`CBJxDrSxGd]VrAB\\n@~GBz@DnAAZEpBo@zXGdCGnDE~CUlLQ~EO`C_@rCi@`C{@zC_AhC_ApB}A~CkRx_@wAnCuA~BoAjBkAzAaB~A}ApA{AfA_BbAiLnGyM|H{JpFaAh@{CfBgShKeH~DcRnK}HlEgTzL}MtHoFvCoIvEiH`EkCxAcB`AmBbAaCtA{@h@w@j@_An@w@n@eAz@cAz@}@v@_A~@iAjAgAlAo@r@}@pAwBpCoB`CqBhCiA|AkDtE}HbKuHzJwH`Ko@|@aBvBoCnD{AnB}@nAoA~AmA`BeC|CkA~A_CzCwBpC}ArBuAhB{ElG_DbE{DdFwBpCGJ_MbP_FpGUVWT]V[TUPUT]`@q@|@OROTMTKRM^Sb@OVS`@yFpH}FpHgLlOEDSPYVi@b@q@l@[\\e@l@e@l@QVY`@MXMTQ`@Sb@[h@QV}G|IiF~GcIjKoMxPiCdDkCjDyH~Jg@p@gDlEuAfBgB`CiDvE{@fAi@r@iAxAc@`@YXURQNQJSHUDYD]By@D]HSHMJILILINGPITM\\MVMVIHKLQJUJk@HgCZuBZaJr@q@FaDReEZqC^cCPcG`@sJx@{Ir@yBNaA@gENqBBe@@kDXa@@a@C[E[S[I[C]BYDa@NKJMNM\\CTAT@XBTHPP\\TN`@l@Zx@F\\B`@Bf@\\tMp@b[JxB`@jHxAto@N`JRhHXnF^xOLrFL~EFbCHjElB|x@t@r\\L~FBvAx@d]\\rNbEnjBZpMZvNFfBZrNd@bTX~Ld@|RJrEJvEJtEZdN\\lN\\|Oj@|U^zO@^TpKTlHJfGF|IHhFFxBZzMl@|W`@pKPlFLxDFzBf@|Ux@x\\\\jHh@pGjApIhAbHR`Aj@bC|AlGr@zBnC~Hf@xAnAtCnAhCnAfC`@r@rA~BlCdEzBbDtB`DxB|CvAjBHLHLzEfHhD~EpI~LlFnIpBfD`A~AtAjCtCtGxCjHjBdFjApDrAtEl@dCvAvGxAfIv@dJFp@z@hJ\\nDd@xEz@xIZlDjAfMt@tHn@zGT~B`@xEZ|CJ~@TdCxFtl@tBzRp@dHp@pHHx@lAbMpCzZnClYtAlNj@fGN`CVbDf@tFbAjKtBbU^tDLvA\\nFd@rFd@`Fp@bHH~@n@fIJ`AjCpXdCdXdE`c@dAbLLvAt@|Hr@zHlAtMp@nLF`AV~ERzEZhIX~MFbJ?hMOzP_@zR_ApSu@fMcA|Ls@jHWfCiAvK}CdZ_DjZ{CxYMtAgC`VoCzWmAvL[bDi@fFwCxXsBxRi@`FcCbVmAnLmAdLcCxUgCnVcCnUgBbQCVa@|DqB`RwBtSkApKuA`Nc@tFKz@q@bHKdAs@xGgAbJOxAq@`HiDl[_@dDwBvRyDb_@oObyAcEz`@yA|M?\\aEtb@Gn@g@rEmChVcFvf@o@~Gg@nEg@tE{@`Je@|EUtBg@dF[tCOdBKxC@j@Bl@HdA\\jBh@jBd@hAh@hA`ArAbC~BpB`BvBfBvE~DxItHlEtD`DlClB~AfBzAvD~CfCzBx@p@|F`FxE|DnGlF|EdErFxEjFnEnErD|GnFhAhA~M~KlKvInAfAvHrGxFhFdH`GrCfClMjKxMdLTH`NlLtIrHbEnDnAbCxBlBJJnCzBlDhC`@^~@bA`@d@R`@L^D^Bj@Af@Mn@Oh@c@p@g@^w@Zg@Hs@LcDr@]HaAR[BY@u@O[GYGWE_@Ai@DcAP_@FIBUJ[Ne@f@s@`A_B~@}Ad@u@P{Cr@eCh@yDr@gGlA{HbBa@H_LtBgBb@kStDyGxAe@JcCd@{@NoARaB\\q@JoG|AiQrDmE|@gGhAwDr@mDt@kDt@qDp@iDp@aAXq@NgF~@_Dh@MB@T@`B?T\\zDf@|D\\~D\\|Dd@~DB\\H`@`@|Cp@xDl@zDVlBFrADx@Ad@Eb@K`@O^QZMLKR_@TuBpBg@`@a@\\gA`AuCtCu@p@cBxA{ChC_@ZkDxCQLDZn@tDn@fEcBXqDr@l@bEvB_@","distancia":"85,6 km","tempo":"1 h 6 min","distanciaNumerica":85551.4,"tempoNumerico":3976.1,"destaque":false}]}